Workbook

Sheet Dashboard
A1: TORNILLERÍA BERCINOX, S.L. · CUADRO DE MANDO DE VENTAS
A2: Datos ficticios. Todos los importes son netos, sin IVA. El cuadro se recalcula solo al cambiar cualquier dato de Ventas, Gastos o Parametros (F9 fuerza el recálculo).
A4: FILTROS
A5: Periodo | B5: Todo el histórico | F5: Criterios aplicados (calculados, no editar)
A6: País | B6: Todos | F6: Desde | G6: =IF($B$5="2025",DATE(2025,1,1),IF($B$5="2026",DATE(2026,1,1),IF($B$5="Últimos 6 meses",DATE(YEAR($G$7),MONTH($G$7)-5,1),IF($B$5="Últimos 12 meses",DATE(YEAR($G$7),MONTH($G$7)-11,1),DATE(2000,1,1))))) -> 36526
A7: Canal | B7: Todos | F7: Hasta | G7: =IF($B$5="2025",DATE(2025,12,31),IF($B$5="2026",DATE(2026,12,31),EOMONTH(MAX(Ventas!$B$2:$B$1620),0))) -> 46203
A8: Actualizado | B8: =TODAY() -> 46232 | F8: País / Canal | G8: =IF($B$6="Todos","*",$B$6) -> * | H8: =IF($B$7="Todos","*",$B$7) -> *
A10: INDICADORES CLAVE DEL PERIODO SELECCIONADO
A11: INGRESOS NETOS | C11: MARGEN CONTRIBUCIÓN | E11: MARGEN % | G11: Nº PEDIDOS | I11: TICKET MEDIO | K11: CAJAS VENDIDAS
A12: =SUMIFS(Ventas!$P$2:$P$1620,Ventas!$B$2:$B$1620,">="&$G$6,Ventas!$B$2:$B$1620,"<="&$G$7,Ventas!$E$2:$E$1620,$G$8,Ventas!$F$2:$F$1620,$H$8) -> 6469595.4 | C12: =SUMIFS(Ventas!$U$2:$U$1620,Ventas!$B$2:$B$1620,">="&$G$6,Ventas!$B$2:$B$1620,"<="&$G$7,Ventas!$E$2:$E$1620,$G$8,Ventas!$F$2:$F$1620,$H$8) -> 1994724.8 | E12: =IFERROR(SUMIFS(Ventas!$U$2:$U$1620,Ventas!$B$2:$B$1620,">="&$G$6,Ventas!$B$2:$B$1620,"<="&$G$7,Ventas!$E$2:$E$1620,$G$8,Ventas!$F$2:$F$1620,$H$8)/SUMIFS(Ventas!$P$2:$P$1620,Ventas!$B$2:$B$1620,">="&$G$6,Ventas!$B$2:$B$1620,"<="&$G$7,Ventas!$E$2:$E$1620,$G$8,Ventas!$F$2:$F$1620,$H$8),0) -> 0.30832296 | G12: =SUMIFS(Ventas!$Y$2:$Y$1620,Ventas!$B$2:$B$1620,">="&$G$6,Ventas!$B$2:$B$1620,"<="&$G$7,Ventas!$E$2:$E$1620,$G$8,Ventas!$F$2:$F$1620,$H$8) -> 868 | I12: =IFERROR(SUMIFS(Ventas!$P$2:$P$1620,Ventas!$B$2:$B$1620,">="&$G$6,Ventas!$B$2:$B$1620,"<="&$G$7,Ventas!$E$2:$E$1620,$G$8,Ventas!$F$2:$F$1620,$H$8)/SUMIFS(Ventas!$Y$2:$Y$1620,Ventas!$B$2:$B$1620,">="&$G$6,Ventas!$B$2:$B$1620,"<="&$G$7,Ventas!$E$2:$E$1620,$G$8,Ventas!$F$2:$F$1620,$H$8),0) -> 7453.4509 | K12: =SUMIFS(Ventas!$L$2:$L$1620,Ventas!$B$2:$B$1620,">="&$G$6,Ventas!$B$2:$B$1620,"<="&$G$7,Ventas!$E$2:$E$1620,$G$8,Ventas!$F$2:$F$1620,$H$8) -> 143110
A14: OBJETIVO PERIODO | C14: CUMPLIMIENTO | E14: GASTOS EXPLOTACIÓN | G14: EBITDA | I14: EBITDA % | K14: COBRO VENCIDO
A15: =IF(AND($B$6="Todos",$B$7="Todos"),SUMIFS(Parametros!$C$26:$C$43,Parametros!$A$26:$A$43,">="&$G$6,Parametros!$A$26:$A$43,"<="&$G$7),"n/d") -> 6490000 | C15: =IF(AND($B$6="Todos",$B$7="Todos"),IFERROR(SUMIFS(Ventas!$P$2:$P$1620,Ventas!$B$2:$B$1620,">="&$G$6,Ventas!$B$2:$B$1620,"<="&$G$7,Ventas!$E$2:$E$1620,$G$8,Ventas!$F$2:$F$1620,$H$8)/SUMIFS(Parametros!$C$26:$C$43,Parametros!$A$26:$A$43,">="&$G$6,Parametros!$A$26:$A$43,"<="&$G$7),0),"n/d") -> 0.996856 | E15: =IF(AND($B$6="Todos",$B$7="Todos"),SUMIFS(Gastos!$D$2:$D$217,Gastos!$A$2:$A$217,">="&$G$6,Gastos!$A$2:$A$217,"<="&$G$7),"n/d") -> 1660812.6 | G15: =IF(AND($B$6="Todos",$B$7="Todos"),SUMIFS(Ventas!$U$2:$U$1620,Ventas!$B$2:$B$1620,">="&$G$6,Ventas!$B$2:$B$1620,"<="&$G$7,Ventas!$E$2:$E$1620,$G$8,Ventas!$F$2:$F$1620,$H$8)-SUMIFS(Gastos!$D$2:$D$217,Gastos!$A$2:$A$217,">="&$G$6,Gastos!$A$2:$A$217,"<="&$G$7),"n/d") -> 333912.2 | I15: =IF(AND($B$6="Todos",$B$7="Todos"),IFERROR((SUMIFS(Ventas!$U$2:$U$1620,Ventas!$B$2:$B$1620,">="&$G$6,Ventas!$B$2:$B$1620,"<="&$G$7,Ventas!$E$2:$E$1620,$G$8,Ventas!$F$2:$F$1620,$H$8)-SUMIFS(Gastos!$D$2:$D$217,Gastos!$A$2:$A$217,">="&$G$6,Gastos!$A$2:$A$217,"<="&$G$7))/SUMIFS(Ventas!$P$2:$P$1620,Ventas!$B$2:$B$1620,">="&$G$6,Ventas!$B$2:$B$1620,"<="&$G$7,Ventas!$E$2:$E$1620,$G$8,Ventas!$F$2:$F$1620,$H$8),0),"n/d") -> 0.051612532 | K15: =SUMIFS(Ventas!$P$2:$P$1620,Ventas!$B$2:$B$1620,">="&$G$6,Ventas!$B$2:$B$1620,"<="&$G$7,Ventas!$E$2:$E$1620,$G$8,Ventas!$F$2:$F$1620,$H$8,Ventas!$X$2:$X$1620,"Vencido") -> 401013.54
A17: Objetivo, gastos y EBITDA solo se calculan con País = Todos y Canal = Todos: los gastos de explotación no están repartidos por país ni por canal. La serie mensual de los gráficos muestra siempre los 18 meses completos y responde a los filtros de País y Canal, no al de Periodo.
A19: EVOLUCIÓN Y MIX
A38: DESGLOSE POR PAÍS, PRODUCTO Y CLIENTE
A56: RENTABILIDAD Y COBROS
A74: T1 · EVOLUCIÓN MENSUAL (filtrada por País y Canal)
A75: Mes | B75: Ingresos netos | C75: Objetivo | D75: Margen contribución | E75: Margen % | F75: Nº pedidos | G75: Ticket medio
A76: =Parametros!$A$26 -> 45658 | B76: =SUMIFS(Ventas!$P$2:$P$1620,Ventas!$C$2:$C$1620,$A76,Ventas!$E$2:$E$1620,$G$8,Ventas!$F$2:$F$1620,$H$8) -> 211137.89 | C76: =IF(AND($B$6="Todos",$B$7="Todos"),INDEX(Parametros!$C$26:$C$43,MATCH($A76,Parametros!$A$26:$A$43,0)),0) -> 300000 | D76: =SUMIFS(Ventas!$U$2:$U$1620,Ventas!$C$2:$C$1620,$A76,Ventas!$E$2:$E$1620,$G$8,Ventas!$F$2:$F$1620,$H$8) -> 66248.749 | E76: =IFERROR(D76/B76,0) -> 0.31377006 | F76: =SUMIFS(Ventas!$Y$2:$Y$1620,Ventas!$C$2:$C$1620,$A76,Ventas!$E$2:$E$1620,$G$8,Ventas!$F$2:$F$1620,$H$8) -> 40 | G76: =IFERROR(B76/F76,0) -> 5278.4473
A77: =Parametros!$A$27 -> 45689 | B77: =SUMIFS(Ventas!$P$2:$P$1620,Ventas!$C$2:$C$1620,$A77,Ventas!$E$2:$E$1620,$G$8,Ventas!$F$2:$F$1620,$H$8) -> 359815.02 | C77: =IF(AND($B$6="Todos",$B$7="Todos"),INDEX(Parametros!$C$26:$C$43,MATCH($A77,Parametros!$A$26:$A$43,0)),0) -> 340000 | D77: =SUMIFS(Ventas!$U$2:$U$1620,Ventas!$C$2:$C$1620,$A77,Ventas!$E$2:$E$1620,$G$8,Ventas!$F$2:$F$1620,$H$8) -> 107300.54 | E77: =IFERROR(D77/B77,0) -> 0.2982103 | F77: =SUMIFS(Ventas!$Y$2:$Y$1620,Ventas!$C$2:$C$1620,$A77,Ventas!$E$2:$E$1620,$G$8,Ventas!$F$2:$F$1620,$H$8) -> 47 | G77: =IFERROR(B77/F77,0) -> 7655.6387
A78: =Parametros!$A$28 -> 45717 | B78: =SUMIFS(Ventas!$P$2:$P$1620,Ventas!$C$2:$C$1620,$A78,Ventas!$E$2:$E$1620,$G$8,Ventas!$F$2:$F$1620,$H$8) -> 402755.5 | C78: =IF(AND($B$6="Todos",$B$7="Todos"),INDEX(Parametros!$C$26:$C$43,MATCH($A78,Parametros!$A$26:$A$43,0)),0) -> 380000 | D78: =SUMIFS(Ventas!$U$2:$U$1620,Ventas!$C$2:$C$1620,$A78,Ventas!$E$2:$E$1620,$G$8,Ventas!$F$2:$F$1620,$H$8) -> 122520.07 | E78: =IFERROR(D78/B78,0) -> 0.30420458 | F78: =SUMIFS(Ventas!$Y$2:$Y$1620,Ventas!$C$2:$C$1620,$A78,Ventas!$E$2:$E$1620,$G$8,Ventas!$F$2:$F$1620,$H$8) -> 52 | G78: =IFERROR(B78/F78,0) -> 7745.298
A79: =Parametros!$A$29 -> 45748 | B79: =SUMIFS(Ventas!$P$2:$P$1620,Ventas!$C$2:$C$1620,$A79,Ventas!$E$2:$E$1620,$G$8,Ventas!$F$2:$F$1620,$H$8) -> 386160.31 | C79: =IF(AND($B$6="Todos",$B$7="Todos"),INDEX(Parametros!$C$26:$C$43,MATCH($A79,Parametros!$A$26:$A$43,0)),0) -> 380000 | D79: =SUMIFS(Ventas!$U$2:$U$1620,Ventas!$C$2:$C$1620,$A79,Ventas!$E$2:$E$1620,$G$8,Ventas!$F$2:$F$1620,$H$8) -> 116546.42 | E79: =IFERROR(D79/B79,0) -> 0.30180839 | F79: =SUMIFS(Ventas!$Y$2:$Y$1620,Ventas!$C$2:$C$1620,$A79,Ventas!$E$2:$E$1620,$G$8,Ventas!$F$2:$F$1620,$H$8) -> 49 | G79: =IFERROR(B79/F79,0) -> 7880.8227
A80: =Parametros!$A$30 -> 45778 | B80: =SUMIFS(Ventas!$P$2:$P$1620,Ventas!$C$2:$C$1620,$A80,Ventas!$E$2:$E$1620,$G$8,Ventas!$F$2:$F$1620,$H$8) -> 366914.69 | C80: =IF(AND($B$6="Todos",$B$7="Todos"),INDEX(Parametros!$C$26:$C$43,MATCH($A80,Parametros!$A$26:$A$43,0)),0) -> 375000 | D80: =SUMIFS(Ventas!$U$2:$U$1620,Ventas!$C$2:$C$1620,$A80,Ventas!$E$2:$E$1620,$G$8,Ventas!$F$2:$F$1620,$H$8) -> 115642.31 | E80: =IFERROR(D80/B80,0) -> 0.31517493 | F80: =SUMIFS(Ventas!$Y$2:$Y$1620,Ventas!$C$2:$C$1620,$A80,Ventas!$E$2:$E$1620,$G$8,Ventas!$F$2:$F$1620,$H$8) -> 55 | G80: =IFERROR(B80/F80,0) -> 6671.1762
A81: =Parametros!$A$31 -> 45809 | B81: =SUMIFS(Ventas!$P$2:$P$1620,Ventas!$C$2:$C$1620,$A81,Ventas!$E$2:$E$1620,$G$8,Ventas!$F$2:$F$1620,$H$8) -> 401613.7 | C81: =IF(AND($B$6="Todos",$B$7="Todos"),INDEX(Parametros!$C$26:$C$43,MATCH($A81,Parametros!$A$26:$A$43,0)),0) -> 385000 | D81: =SUMIFS(Ventas!$U$2:$U$1620,Ventas!$C$2:$C$1620,$A81,Ventas!$E$2:$E$1620,$G$8,Ventas!$F$2:$F$1620,$H$8) -> 124394.88 | E81: =IFERROR(D81/B81,0) -> 0.30973764 | F81: =SUMIFS(Ventas!$Y$2:$Y$1620,Ventas!$C$2:$C$1620,$A81,Ventas!$E$2:$E$1620,$G$8,Ventas!$F$2:$F$1620,$H$8) -> 48 | G81: =IFERROR(B81/F81,0) -> 8366.9521
A82: =Parametros!$A$32 -> 45839 | B82: =SUMIFS(Ventas!$P$2:$P$1620,Ventas!$C$2:$C$1620,$A82,Ventas!$E$2:$E$1620,$G$8,Ventas!$F$2:$F$1620,$H$8) -> 369003.3 | C82: =IF(AND($B$6="Todos",$B$7="Todos"),INDEX(Parametros!$C$26:$C$43,MATCH($A82,Parametros!$A$26:$A$43,0)),0) -> 360000 | D82: =SUMIFS(Ventas!$U$2:$U$1620,Ventas!$C$2:$C$1620,$A82,Ventas!$E$2:$E$1620,$G$8,Ventas!$F$2:$F$1620,$H$8) -> 111833.49 | E82: =IFERROR(D82/B82,0) -> 0.30306908 | F82: =SUMIFS(Ventas!$Y$2:$Y$1620,Ventas!$C$2:$C$1620,$A82,Ventas!$E$2:$E$1620,$G$8,Ventas!$F$2:$F$1620,$H$8) -> 46 | G82: =IFERROR(B82/F82,0) -> 8021.8109
A83: =Parametros!$A$33 -> 45870 | B83: =SUMIFS(Ventas!$P$2:$P$1620,Ventas!$C$2:$C$1620,$A83,Ventas!$E$2:$E$1620,$G$8,Ventas!$F$2:$F$1620,$H$8) -> 244108.86 | C83: =IF(AND($B$6="Todos",$B$7="Todos"),INDEX(Parametros!$C$26:$C$43,MATCH($A83,Parametros!$A$26:$A$43,0)),0) -> 250000 | D83: =SUMIFS(Ventas!$U$2:$U$1620,Ventas!$C$2:$C$1620,$A83,Ventas!$E$2:$E$1620,$G$8,Ventas!$F$2:$F$1620,$H$8) -> 75143.155 | E83: =IFERROR(D83/B83,0) -> 0.30782642 | F83: =SUMIFS(Ventas!$Y$2:$Y$1620,Ventas!$C$2:$C$1620,$A83,Ventas!$E$2:$E$1620,$G$8,Ventas!$F$2:$F$1620,$H$8) -> 33 | G83: =IFERROR(B83/F83,0) -> 7397.2381
A84: =Parametros!$A$34 -> 45901 | B84: =SUMIFS(Ventas!$P$2:$P$1620,Ventas!$C$2:$C$1620,$A84,Ventas!$E$2:$E$1620,$G$8,Ventas!$F$2:$F$1620,$H$8) -> 333535.39 | C84: =IF(AND($B$6="Todos",$B$7="Todos"),INDEX(Parametros!$C$26:$C$43,MATCH($A84,Parametros!$A$26:$A$43,0)),0) -> 340000 | D84: =SUMIFS(Ventas!$U$2:$U$1620,Ventas!$C$2:$C$1620,$A84,Ventas!$E$2:$E$1620,$G$8,Ventas!$F$2:$F$1620,$H$8) -> 100441.16 | E84: =IFERROR(D84/B84,0) -> 0.30114093 | F84: =SUMIFS(Ventas!$Y$2:$Y$1620,Ventas!$C$2:$C$1620,$A84,Ventas!$E$2:$E$1620,$G$8,Ventas!$F$2:$F$1620,$H$8) -> 47 | G84: =IFERROR(B84/F84,0) -> 7096.4976
A85: =Parametros!$A$35 -> 45931 | B85: =SUMIFS(Ventas!$P$2:$P$1620,Ventas!$C$2:$C$1620,$A85,Ventas!$E$2:$E$1620,$G$8,Ventas!$F$2:$F$1620,$H$8) -> 361634.8 | C85: =IF(AND($B$6="Todos",$B$7="Todos"),INDEX(Parametros!$C$26:$C$43,MATCH($A85,Parametros!$A$26:$A$43,0)),0) -> 370000 | D85: =SUMIFS(Ventas!$U$2:$U$1620,Ventas!$C$2:$C$1620,$A85,Ventas!$E$2:$E$1620,$G$8,Ventas!$F$2:$F$1620,$H$8) -> 106710.03 | E85: =IFERROR(D85/B85,0) -> 0.29507677 | F85: =SUMIFS(Ventas!$Y$2:$Y$1620,Ventas!$C$2:$C$1620,$A85,Ventas!$E$2:$E$1620,$G$8,Ventas!$F$2:$F$1620,$H$8) -> 54 | G85: =IFERROR(B85/F85,0) -> 6696.9408
A86: =Parametros!$A$36 -> 45962 | B86: =SUMIFS(Ventas!$P$2:$P$1620,Ventas!$C$2:$C$1620,$A86,Ventas!$E$2:$E$1620,$G$8,Ventas!$F$2:$F$1620,$H$8) -> 432903.56 | C86: =IF(AND($B$6="Todos",$B$7="Todos"),INDEX(Parametros!$C$26:$C$43,MATCH($A86,Parametros!$A$26:$A$43,0)),0) -> 390000 | D86: =SUMIFS(Ventas!$U$2:$U$1620,Ventas!$C$2:$C$1620,$A86,Ventas!$E$2:$E$1620,$G$8,Ventas!$F$2:$F$1620,$H$8) -> 128470.23 | E86: =IFERROR(D86/B86,0) -> 0.2967641 | F86: =SUMIFS(Ventas!$Y$2:$Y$1620,Ventas!$C$2:$C$1620,$A86,Ventas!$E$2:$E$1620,$G$8,Ventas!$F$2:$F$1620,$H$8) -> 49 | G86: =IFERROR(B86/F86,0) -> 8834.7666
A87: =Parametros!$A$37 -> 45992 | B87: =SUMIFS(Ventas!$P$2:$P$1620,Ventas!$C$2:$C$1620,$A87,Ventas!$E$2:$E$1620,$G$8,Ventas!$F$2:$F$1620,$H$8) -> 369951.02 | C87: =IF(AND($B$6="Todos",$B$7="Todos"),INDEX(Parametros!$C$26:$C$43,MATCH($A87,Parametros!$A$26:$A$43,0)),0) -> 360000 | D87: =SUMIFS(Ventas!$U$2:$U$1620,Ventas!$C$2:$C$1620,$A87,Ventas!$E$2:$E$1620,$G$8,Ventas!$F$2:$F$1620,$H$8) -> 112764.72 | E87: =IFERROR(D87/B87,0) -> 0.30480986 | F87: =SUMIFS(Ventas!$Y$2:$Y$1620,Ventas!$C$2:$C$1620,$A87,Ventas!$E$2:$E$1620,$G$8,Ventas!$F$2:$F$1620,$H$8) -> 43 | G87: =IFERROR(B87/F87,0) -> 8603.512
A88: =Parametros!$A$38 -> 46023 | B88: =SUMIFS(Ventas!$P$2:$P$1620,Ventas!$C$2:$C$1620,$A88,Ventas!$E$2:$E$1620,$G$8,Ventas!$F$2:$F$1620,$H$8) -> 337299.01 | C88: =IF(AND($B$6="Todos",$B$7="Todos"),INDEX(Parametros!$C$26:$C$43,MATCH($A88,Parametros!$A$26:$A$43,0)),0) -> 335000 | D88: =SUMIFS(Ventas!$U$2:$U$1620,Ventas!$C$2:$C$1620,$A88,Ventas!$E$2:$E$1620,$G$8,Ventas!$F$2:$F$1620,$H$8) -> 102401.48 | E88: =IFERROR(D88/B88,0) -> 0.30359258 | F88: =SUMIFS(Ventas!$Y$2:$Y$1620,Ventas!$C$2:$C$1620,$A88,Ventas!$E$2:$E$1620,$G$8,Ventas!$F$2:$F$1620,$H$8) -> 42 | G88: =IFERROR(B88/F88,0) -> 8030.9288
A89: =Parametros!$A$39 -> 46054 | B89: =SUMIFS(Ventas!$P$2:$P$1620,Ventas!$C$2:$C$1620,$A89,Ventas!$E$2:$E$1620,$G$8,Ventas!$F$2:$F$1620,$H$8) -> 352386.62 | C89: =IF(AND($B$6="Todos",$B$7="Todos"),INDEX(Parametros!$C$26:$C$43,MATCH($A89,Parametros!$A$26:$A$43,0)),0) -> 355000 | D89: =SUMIFS(Ventas!$U$2:$U$1620,Ventas!$C$2:$C$1620,$A89,Ventas!$E$2:$E$1620,$G$8,Ventas!$F$2:$F$1620,$H$8) -> 107815.01 | E89: =IFERROR(D89/B89,0) -> 0.30595659 | F89: =SUMIFS(Ventas!$Y$2:$Y$1620,Ventas!$C$2:$C$1620,$A89,Ventas!$E$2:$E$1620,$G$8,Ventas!$F$2:$F$1620,$H$8) -> 48 | G89: =IFERROR(B89/F89,0) -> 7341.388
A90: =Parametros!$A$40 -> 46082 | B90: =SUMIFS(Ventas!$P$2:$P$1620,Ventas!$C$2:$C$1620,$A90,Ventas!$E$2:$E$1620,$G$8,Ventas!$F$2:$F$1620,$H$8) -> 398590.96 | C90: =IF(AND($B$6="Todos",$B$7="Todos"),INDEX(Parametros!$C$26:$C$43,MATCH($A90,Parametros!$A$26:$A$43,0)),0) -> 400000 | D90: =SUMIFS(Ventas!$U$2:$U$1620,Ventas!$C$2:$C$1620,$A90,Ventas!$E$2:$E$1620,$G$8,Ventas!$F$2:$F$1620,$H$8) -> 125939.39 | E90: =IFERROR(D90/B90,0) -> 0.31596148 | F90: =SUMIFS(Ventas!$Y$2:$Y$1620,Ventas!$C$2:$C$1620,$A90,Ventas!$E$2:$E$1620,$G$8,Ventas!$F$2:$F$1620,$H$8) -> 52 | G90: =IFERROR(B90/F90,0) -> 7665.2108
A91: =Parametros!$A$41 -> 46113 | B91: =SUMIFS(Ventas!$P$2:$P$1620,Ventas!$C$2:$C$1620,$A91,Ventas!$E$2:$E$1620,$G$8,Ventas!$F$2:$F$1620,$H$8) -> 393675.57 | C91: =IF(AND($B$6="Todos",$B$7="Todos"),INDEX(Parametros!$C$26:$C$43,MATCH($A91,Parametros!$A$26:$A$43,0)),0) -> 400000 | D91: =SUMIFS(Ventas!$U$2:$U$1620,Ventas!$C$2:$C$1620,$A91,Ventas!$E$2:$E$1620,$G$8,Ventas!$F$2:$F$1620,$H$8) -> 129818.15 | E91: =IFERROR(D91/B91,0) -> 0.32975922 | F91: =SUMIFS(Ventas!$Y$2:$Y$1620,Ventas!$C$2:$C$1620,$A91,Ventas!$E$2:$E$1620,$G$8,Ventas!$F$2:$F$1620,$H$8) -> 57 | G91: =IFERROR(B91/F91,0) -> 6906.5889
A92: =Parametros!$A$42 -> 46143 | B92: =SUMIFS(Ventas!$P$2:$P$1620,Ventas!$C$2:$C$1620,$A92,Ventas!$E$2:$E$1620,$G$8,Ventas!$F$2:$F$1620,$H$8) -> 398935.23 | C92: =IF(AND($B$6="Todos",$B$7="Todos"),INDEX(Parametros!$C$26:$C$43,MATCH($A92,Parametros!$A$26:$A$43,0)),0) -> 400000 | D92: =SUMIFS(Ventas!$U$2:$U$1620,Ventas!$C$2:$C$1620,$A92,Ventas!$E$2:$E$1620,$G$8,Ventas!$F$2:$F$1620,$H$8) -> 130917.21 | E92: =IFERROR(D92/B92,0) -> 0.32816656 | F92: =SUMIFS(Ventas!$Y$2:$Y$1620,Ventas!$C$2:$C$1620,$A92,Ventas!$E$2:$E$1620,$G$8,Ventas!$F$2:$F$1620,$H$8) -> 56 | G92: =IFERROR(B92/F92,0) -> 7123.8435
A93: =Parametros!$A$43 -> 46174 | B93: =SUMIFS(Ventas!$P$2:$P$1620,Ventas!$C$2:$C$1620,$A93,Ventas!$E$2:$E$1620,$G$8,Ventas!$F$2:$F$1620,$H$8) -> 349173.98 | C93: =IF(AND($B$6="Todos",$B$7="Todos"),INDEX(Parametros!$C$26:$C$43,MATCH($A93,Parametros!$A$26:$A$43,0)),0) -> 370000 | D93: =SUMIFS(Ventas!$U$2:$U$1620,Ventas!$C$2:$C$1620,$A93,Ventas!$E$2:$E$1620,$G$8,Ventas!$F$2:$F$1620,$H$8) -> 109817.82 | E93: =IFERROR(D93/B93,0) -> 0.31450746 | F93: =SUMIFS(Ventas!$Y$2:$Y$1620,Ventas!$C$2:$C$1620,$A93,Ventas!$E$2:$E$1620,$G$8,Ventas!$F$2:$F$1620,$H$8) -> 50 | G93: =IFERROR(B93/F93,0) -> 6983.4797
A94: TOTAL | B94: =SUM(B76:B93) -> 6469595.4 | C94: =SUM(C76:C93) -> 6490000 | D94: =SUM(D76:D93) -> 1994724.8 | E94: =IFERROR(D94/B94,0) -> 0.30832296 | F94: =SUM(F76:F93) -> 868 | G94: =IFERROR(B94/F94,0) -> 7453.4509
A96: T2 · VENTAS POR PAÍS
A97: País | B97: Ingresos netos | C97: Margen contribución | D97: Margen % | E97: % s/ total
A98: España | B98: =SUMIFS(Ventas!$P$2:$P$1620,Ventas!$E$2:$E$1620,$A98,Ventas!$B$2:$B$1620,">="&$G$6,Ventas!$B$2:$B$1620,"<="&$G$7,Ventas!$F$2:$F$1620,$H$8) -> 3440618 | C98: =SUMIFS(Ventas!$U$2:$U$1620,Ventas!$E$2:$E$1620,$A98,Ventas!$B$2:$B$1620,">="&$G$6,Ventas!$B$2:$B$1620,"<="&$G$7,Ventas!$F$2:$F$1620,$H$8) -> 1110498.4 | D98: =IFERROR(C98/B98,0) -> 0.32276132 | E98: =IFERROR(B98/$B$101,0) -> 0.53181347
A99: Alemania | B99: =SUMIFS(Ventas!$P$2:$P$1620,Ventas!$E$2:$E$1620,$A99,Ventas!$B$2:$B$1620,">="&$G$6,Ventas!$B$2:$B$1620,"<="&$G$7,Ventas!$F$2:$F$1620,$H$8) -> 1760409.4 | C99: =SUMIFS(Ventas!$U$2:$U$1620,Ventas!$E$2:$E$1620,$A99,Ventas!$B$2:$B$1620,">="&$G$6,Ventas!$B$2:$B$1620,"<="&$G$7,Ventas!$F$2:$F$1620,$H$8) -> 501447.09 | D99: =IFERROR(C99/B99,0) -> 0.28484686 | E99: =IFERROR(B99/$B$101,0) -> 0.27210502
A100: Francia | B100: =SUMIFS(Ventas!$P$2:$P$1620,Ventas!$E$2:$E$1620,$A100,Ventas!$B$2:$B$1620,">="&$G$6,Ventas!$B$2:$B$1620,"<="&$G$7,Ventas!$F$2:$F$1620,$H$8) -> 1268568 | C100: =SUMIFS(Ventas!$U$2:$U$1620,Ventas!$E$2:$E$1620,$A100,Ventas!$B$2:$B$1620,">="&$G$6,Ventas!$B$2:$B$1620,"<="&$G$7,Ventas!$F$2:$F$1620,$H$8) -> 382779.33 | D100: =IFERROR(C100/B100,0) -> 0.30174127 | E100: =IFERROR(B100/$B$101,0) -> 0.19608151
A101: TOTAL | B101: =SUM(B98:B100) -> 6469595.4 | C101: =SUM(C98:C100) -> 1994724.8 | D101: =IFERROR(C101/B101,0) -> 0.30832296 | E101: =IFERROR(B101/B101,0) -> 1
A103: T3 · VENTAS POR CANAL
A104: Canal | B104: Ingresos netos | C104: Margen contribución | D104: Margen % | E104: % s/ total
A105: Distribuidor | B105: =SUMIFS(Ventas!$P$2:$P$1620,Ventas!$F$2:$F$1620,$A105,Ventas!$B$2:$B$1620,">="&$G$6,Ventas!$B$2:$B$1620,"<="&$G$7,Ventas!$E$2:$E$1620,$G$8) -> 3245561.4 | C105: =SUMIFS(Ventas!$U$2:$U$1620,Ventas!$F$2:$F$1620,$A105,Ventas!$B$2:$B$1620,">="&$G$6,Ventas!$B$2:$B$1620,"<="&$G$7,Ventas!$E$2:$E$1620,$G$8) -> 940030.93 | D105: =IFERROR(C105/B105,0) -> 0.28963585 | E105: =IFERROR(B105/$B$109,0) -> 0.50166373
A106: OEM / Industria | B106: =SUMIFS(Ventas!$P$2:$P$1620,Ventas!$F$2:$F$1620,$A106,Ventas!$B$2:$B$1620,">="&$G$6,Ventas!$B$2:$B$1620,"<="&$G$7,Ventas!$E$2:$E$1620,$G$8) -> 2377293.7 | C106: =SUMIFS(Ventas!$U$2:$U$1620,Ventas!$F$2:$F$1620,$A106,Ventas!$B$2:$B$1620,">="&$G$6,Ventas!$B$2:$B$1620,"<="&$G$7,Ventas!$E$2:$E$1620,$G$8) -> 745642.26 | D106: =IFERROR(C106/B106,0) -> 0.31365172 | E106: =IFERROR(B106/$B$109,0) -> 0.36745631
A107: Ferretería | B107: =SUMIFS(Ventas!$P$2:$P$1620,Ventas!$F$2:$F$1620,$A107,Ventas!$B$2:$B$1620,">="&$G$6,Ventas!$B$2:$B$1620,"<="&$G$7,Ventas!$E$2:$E$1620,$G$8) -> 802151.76 | C107: =SUMIFS(Ventas!$U$2:$U$1620,Ventas!$F$2:$F$1620,$A107,Ventas!$B$2:$B$1620,">="&$G$6,Ventas!$B$2:$B$1620,"<="&$G$7,Ventas!$E$2:$E$1620,$G$8) -> 290078.2 | D107: =IFERROR(C107/B107,0) -> 0.36162509 | E107: =IFERROR(B107/$B$109,0) -> 0.12398793
A108: Ecommerce | B108: =SUMIFS(Ventas!$P$2:$P$1620,Ventas!$F$2:$F$1620,$A108,Ventas!$B$2:$B$1620,">="&$G$6,Ventas!$B$2:$B$1620,"<="&$G$7,Ventas!$E$2:$E$1620,$G$8) -> 44588.633 | C108: =SUMIFS(Ventas!$U$2:$U$1620,Ventas!$F$2:$F$1620,$A108,Ventas!$B$2:$B$1620,">="&$G$6,Ventas!$B$2:$B$1620,"<="&$G$7,Ventas!$E$2:$E$1620,$G$8) -> 18973.418 | D108: =IFERROR(C108/B108,0) -> 0.42552142 | E108: =IFERROR(B108/$B$109,0) -> 0.006892028
A109: TOTAL | B109: =SUM(B105:B108) -> 6469595.4 | C109: =SUM(C105:C108) -> 1994724.8 | D109: =IFERROR(C109/B109,0) -> 0.30832296 | E109: =IFERROR(B109/B109,0) -> 1
A111: T4 · VENTAS POR FAMILIA DE PRODUCTO
A112: Familia | B112: Ingresos netos | C112: Margen contribución | D112: Margen % | E112: % s/ total
A113: Autotaladrante | B113: =SUMIFS(Ventas!$P$2:$P$1620,Ventas!$J$2:$J$1620,$A113,Ventas!$B$2:$B$1620,">="&$G$6,Ventas!$B$2:$B$1620,"<="&$G$7,Ventas!$E$2:$E$1620,$G$8,Ventas!$F$2:$F$1620,$H$8) -> 689498.52 | C113: =SUMIFS(Ventas!$U$2:$U$1620,Ventas!$J$2:$J$1620,$A113,Ventas!$B$2:$B$1620,">="&$G$6,Ventas!$B$2:$B$1620,"<="&$G$7,Ventas!$E$2:$E$1620,$G$8,Ventas!$F$2:$F$1620,$H$8) -> 208206.16 | D113: =IFERROR(C113/B113,0) -> 0.30196753 | E113: =IFERROR(B113/$B$118,0) -> 0.10657521
A114: Especial | B114: =SUMIFS(Ventas!$P$2:$P$1620,Ventas!$J$2:$J$1620,$A114,Ventas!$B$2:$B$1620,">="&$G$6,Ventas!$B$2:$B$1620,"<="&$G$7,Ventas!$E$2:$E$1620,$G$8,Ventas!$F$2:$F$1620,$H$8) -> 1738284.3 | C114: =SUMIFS(Ventas!$U$2:$U$1620,Ventas!$J$2:$J$1620,$A114,Ventas!$B$2:$B$1620,">="&$G$6,Ventas!$B$2:$B$1620,"<="&$G$7,Ventas!$E$2:$E$1620,$G$8,Ventas!$F$2:$F$1620,$H$8) -> 544611.04 | D114: =IFERROR(C114/B114,0) -> 0.31330379 | E114: =IFERROR(B114/$B$118,0) -> 0.26868516
A115: Inoxidable | B115: =SUMIFS(Ventas!$P$2:$P$1620,Ventas!$J$2:$J$1620,$A115,Ventas!$B$2:$B$1620,">="&$G$6,Ventas!$B$2:$B$1620,"<="&$G$7,Ventas!$E$2:$E$1620,$G$8,Ventas!$F$2:$F$1620,$H$8) -> 1557648.5 | C115: =SUMIFS(Ventas!$U$2:$U$1620,Ventas!$J$2:$J$1620,$A115,Ventas!$B$2:$B$1620,">="&$G$6,Ventas!$B$2:$B$1620,"<="&$G$7,Ventas!$E$2:$E$1620,$G$8,Ventas!$F$2:$F$1620,$H$8) -> 494551.34 | D115: =IFERROR(C115/B115,0) -> 0.31749867 | E115: =IFERROR(B115/$B$118,0) -> 0.24076444
A116: Madera | B116: =SUMIFS(Ventas!$P$2:$P$1620,Ventas!$J$2:$J$1620,$A116,Ventas!$B$2:$B$1620,">="&$G$6,Ventas!$B$2:$B$1620,"<="&$G$7,Ventas!$E$2:$E$1620,$G$8,Ventas!$F$2:$F$1620,$H$8) -> 599495.6 | C116: =SUMIFS(Ventas!$U$2:$U$1620,Ventas!$J$2:$J$1620,$A116,Ventas!$B$2:$B$1620,">="&$G$6,Ventas!$B$2:$B$1620,"<="&$G$7,Ventas!$E$2:$E$1620,$G$8,Ventas!$F$2:$F$1620,$H$8) -> 169585.56 | D116: =IFERROR(C116/B116,0) -> 0.28288041 | E116: =IFERROR(B116/$B$118,0) -> 0.092663537
A117: Métrica | B117: =SUMIFS(Ventas!$P$2:$P$1620,Ventas!$J$2:$J$1620,$A117,Ventas!$B$2:$B$1620,">="&$G$6,Ventas!$B$2:$B$1620,"<="&$G$7,Ventas!$E$2:$E$1620,$G$8,Ventas!$F$2:$F$1620,$H$8) -> 1884668.5 | C117: =SUMIFS(Ventas!$U$2:$U$1620,Ventas!$J$2:$J$1620,$A117,Ventas!$B$2:$B$1620,">="&$G$6,Ventas!$B$2:$B$1620,"<="&$G$7,Ventas!$E$2:$E$1620,$G$8,Ventas!$F$2:$F$1620,$H$8) -> 577770.71 | D117: =IFERROR(C117/B117,0) -> 0.30656358 | E117: =IFERROR(B117/$B$118,0) -> 0.29131165
A118: TOTAL | B118: =SUM(B113:B117) -> 6469595.4 | C118: =SUM(C113:C117) -> 1994724.8 | D118: =IFERROR(C118/B118,0) -> 0.30832296 | E118: =IFERROR(B118/B118,0) -> 1
A120: T5 · VENTAS POR COMERCIAL
A121: Comercial | B121: Ingresos netos | C121: Margen contribución | D121: Margen % | E121: % s/ total
A122: Alberto Ruiz | B122: =SUMIFS(Ventas!$P$2:$P$1620,Ventas!$G$2:$G$1620,$A122,Ventas!$B$2:$B$1620,">="&$G$6,Ventas!$B$2:$B$1620,"<="&$G$7,Ventas!$E$2:$E$1620,$G$8,Ventas!$F$2:$F$1620,$H$8) -> 2044959.5 | C122: =SUMIFS(Ventas!$U$2:$U$1620,Ventas!$G$2:$G$1620,$A122,Ventas!$B$2:$B$1620,">="&$G$6,Ventas!$B$2:$B$1620,"<="&$G$7,Ventas!$E$2:$E$1620,$G$8,Ventas!$F$2:$F$1620,$H$8) -> 660233.7 | D122: =IFERROR(C122/B122,0) -> 0.32285906 | E122: =IFERROR(B122/$B$127,0) -> 0.31608769
A123: Camille Girard | B123: =SUMIFS(Ventas!$P$2:$P$1620,Ventas!$G$2:$G$1620,$A123,Ventas!$B$2:$B$1620,">="&$G$6,Ventas!$B$2:$B$1620,"<="&$G$7,Ventas!$E$2:$E$1620,$G$8,Ventas!$F$2:$F$1620,$H$8) -> 1268568 | C123: =SUMIFS(Ventas!$U$2:$U$1620,Ventas!$G$2:$G$1620,$A123,Ventas!$B$2:$B$1620,">="&$G$6,Ventas!$B$2:$B$1620,"<="&$G$7,Ventas!$E$2:$E$1620,$G$8,Ventas!$F$2:$F$1620,$H$8) -> 382779.33 | D123: =IFERROR(C123/B123,0) -> 0.30174127 | E123: =IFERROR(B123/$B$127,0) -> 0.19608151
A124: Canal online | B124: =SUMIFS(Ventas!$P$2:$P$1620,Ventas!$G$2:$G$1620,$A124,Ventas!$B$2:$B$1620,">="&$G$6,Ventas!$B$2:$B$1620,"<="&$G$7,Ventas!$E$2:$E$1620,$G$8,Ventas!$F$2:$F$1620,$H$8) -> 44588.633 | C124: =SUMIFS(Ventas!$U$2:$U$1620,Ventas!$G$2:$G$1620,$A124,Ventas!$B$2:$B$1620,">="&$G$6,Ventas!$B$2:$B$1620,"<="&$G$7,Ventas!$E$2:$E$1620,$G$8,Ventas!$F$2:$F$1620,$H$8) -> 18973.418 | D124: =IFERROR(C124/B124,0) -> 0.42552142 | E124: =IFERROR(B124/$B$127,0) -> 0.006892028
A125: Klaus Berger | B125: =SUMIFS(Ventas!$P$2:$P$1620,Ventas!$G$2:$G$1620,$A125,Ventas!$B$2:$B$1620,">="&$G$6,Ventas!$B$2:$B$1620,"<="&$G$7,Ventas!$E$2:$E$1620,$G$8,Ventas!$F$2:$F$1620,$H$8) -> 1760409.4 | C125: =SUMIFS(Ventas!$U$2:$U$1620,Ventas!$G$2:$G$1620,$A125,Ventas!$B$2:$B$1620,">="&$G$6,Ventas!$B$2:$B$1620,"<="&$G$7,Ventas!$E$2:$E$1620,$G$8,Ventas!$F$2:$F$1620,$H$8) -> 501447.09 | D125: =IFERROR(C125/B125,0) -> 0.28484686 | E125: =IFERROR(B125/$B$127,0) -> 0.27210502
A126: Nuria Salas | B126: =SUMIFS(Ventas!$P$2:$P$1620,Ventas!$G$2:$G$1620,$A126,Ventas!$B$2:$B$1620,">="&$G$6,Ventas!$B$2:$B$1620,"<="&$G$7,Ventas!$E$2:$E$1620,$G$8,Ventas!$F$2:$F$1620,$H$8) -> 1351069.9 | C126: =SUMIFS(Ventas!$U$2:$U$1620,Ventas!$G$2:$G$1620,$A126,Ventas!$B$2:$B$1620,">="&$G$6,Ventas!$B$2:$B$1620,"<="&$G$7,Ventas!$E$2:$E$1620,$G$8,Ventas!$F$2:$F$1620,$H$8) -> 431291.28 | D126: =IFERROR(C126/B126,0) -> 0.31922203 | E126: =IFERROR(B126/$B$127,0) -> 0.20883375
A127: TOTAL | B127: =SUM(B122:B126) -> 6469595.4 | C127: =SUM(C122:C126) -> 1994724.8 | D127: =IFERROR(C127/B127,0) -> 0.30832296 | E127: =IFERROR(B127/B127,0) -> 1
A129: T6 · SITUACIÓN DE COBRO
A130: Estado | B130: Importe | C130: Nº líneas | D130: % s/ total
A131: Cobrado | B131: =SUMIFS(Ventas!$P$2:$P$1620,Ventas!$B$2:$B$1620,">="&$G$6,Ventas!$B$2:$B$1620,"<="&$G$7,Ventas!$E$2:$E$1620,$G$8,Ventas!$F$2:$F$1620,$H$8,Ventas!$X$2:$X$1620,$A131) -> 5702077.5 | C131: =COUNTIFS(Ventas!$B$2:$B$1620,">="&$G$6,Ventas!$B$2:$B$1620,"<="&$G$7,Ventas!$E$2:$E$1620,$G$8,Ventas!$F$2:$F$1620,$H$8,Ventas!$X$2:$X$1620,$A131) -> 1432 | D131: =IFERROR(B131/$B$134,0) -> 0.88136539
A132: Pendiente | B132: =SUMIFS(Ventas!$P$2:$P$1620,Ventas!$B$2:$B$1620,">="&$G$6,Ventas!$B$2:$B$1620,"<="&$G$7,Ventas!$E$2:$E$1620,$G$8,Ventas!$F$2:$F$1620,$H$8,Ventas!$X$2:$X$1620,$A132) -> 366504.4 | C132: =COUNTIFS(Ventas!$B$2:$B$1620,">="&$G$6,Ventas!$B$2:$B$1620,"<="&$G$7,Ventas!$E$2:$E$1620,$G$8,Ventas!$F$2:$F$1620,$H$8,Ventas!$X$2:$X$1620,$A132) -> 89 | D132: =IFERROR(B132/$B$134,0) -> 0.056650282
A133: Vencido | B133: =SUMIFS(Ventas!$P$2:$P$1620,Ventas!$B$2:$B$1620,">="&$G$6,Ventas!$B$2:$B$1620,"<="&$G$7,Ventas!$E$2:$E$1620,$G$8,Ventas!$F$2:$F$1620,$H$8,Ventas!$X$2:$X$1620,$A133) -> 401013.54 | C133: =COUNTIFS(Ventas!$B$2:$B$1620,">="&$G$6,Ventas!$B$2:$B$1620,"<="&$G$7,Ventas!$E$2:$E$1620,$G$8,Ventas!$F$2:$F$1620,$H$8,Ventas!$X$2:$X$1620,$A133) -> 98 | D133: =IFERROR(B133/$B$134,0) -> 0.06198433
A134: TOTAL | B134: =SUM(B131:B133) -> 6469595.4 | C134: =SUM(C131:C133) -> 1619 | D134: =IFERROR(B134/B134,0) -> 1
A136: T7 · TOP 10 CLIENTES DEL PERIODO
A137: # | B137: Cliente | C137: Ingresos netos | D137: Margen contribución | E137: Margen %
A138: 1 | B138: =IFERROR(INDEX($H$156:$H$193,MATCH(LARGE($I$156:$I$193,A138),$I$156:$I$193,0)),"—") -> Hanseatic Fasteners GmbH | C138: =IFERROR(LARGE($I$156:$I$193,A138),0) -> 313935.47 | D138: =IFERROR(SUMIFS(Ventas!$U$2:$U$1620,Ventas!$D$2:$D$1620,$B138,Ventas!$B$2:$B$1620,">="&$G$6,Ventas!$B$2:$B$1620,"<="&$G$7,Ventas!$E$2:$E$1620,$G$8,Ventas!$F$2:$F$1620,$H$8),0) -> 86703.112 | E138: =IFERROR(D138/C138,0) -> 0.27618132
A139: 2 | B139: =IFERROR(INDEX($H$156:$H$193,MATCH(LARGE($I$156:$I$193,A139),$I$156:$I$193,0)),"—") -> Montajes Industriales Vigo SL | C139: =IFERROR(LARGE($I$156:$I$193,A139),0) -> 290874.72 | D139: =IFERROR(SUMIFS(Ventas!$U$2:$U$1620,Ventas!$D$2:$D$1620,$B139,Ventas!$B$2:$B$1620,">="&$G$6,Ventas!$B$2:$B$1620,"<="&$G$7,Ventas!$E$2:$E$1620,$G$8,Ventas!$F$2:$F$1620,$H$8),0) -> 94487.013 | E139: =IFERROR(D139/C139,0) -> 0.32483748
A140: 3 | B140: =IFERROR(INDEX($H$156:$H$193,MATCH(LARGE($I$156:$I$193,A140),$I$156:$I$193,0)),"—") -> Bayern Befestigung GmbH | C140: =IFERROR(LARGE($I$156:$I$193,A140),0) -> 279795.15 | D140: =IFERROR(SUMIFS(Ventas!$U$2:$U$1620,Ventas!$D$2:$D$1620,$B140,Ventas!$B$2:$B$1620,">="&$G$6,Ventas!$B$2:$B$1620,"<="&$G$7,Ventas!$E$2:$E$1620,$G$8,Ventas!$F$2:$F$1620,$H$8),0) -> 76639.395 | E140: =IFERROR(D140/C140,0) -> 0.27391252
A141: 4 | B141: =IFERROR(INDEX($H$156:$H$193,MATCH(LARGE($I$156:$I$193,A141),$I$156:$I$193,0)),"—") -> Schrauben Nord GmbH | C141: =IFERROR(LARGE($I$156:$I$193,A141),0) -> 279560.77 | D141: =IFERROR(SUMIFS(Ventas!$U$2:$U$1620,Ventas!$D$2:$D$1620,$B141,Ventas!$B$2:$B$1620,">="&$G$6,Ventas!$B$2:$B$1620,"<="&$G$7,Ventas!$E$2:$E$1620,$G$8,Ventas!$F$2:$F$1620,$H$8),0) -> 77428.641 | E141: =IFERROR(D141/C141,0) -> 0.27696533
A142: 5 | B142: =IFERROR(INDEX($H$156:$H$193,MATCH(LARGE($I$156:$I$193,A142),$I$156:$I$193,0)),"—") -> Aceros del Norte SA | C142: =IFERROR(LARGE($I$156:$I$193,A142),0) -> 268007.9 | D142: =IFERROR(SUMIFS(Ventas!$U$2:$U$1620,Ventas!$D$2:$D$1620,$B142,Ventas!$B$2:$B$1620,">="&$G$6,Ventas!$B$2:$B$1620,"<="&$G$7,Ventas!$E$2:$E$1620,$G$8,Ventas!$F$2:$F$1620,$H$8),0) -> 80096.429 | E142: =IFERROR(D142/C142,0) -> 0.29885846
A143: 6 | B143: =IFERROR(INDEX($H$156:$H$193,MATCH(LARGE($I$156:$I$193,A143),$I$156:$I$193,0)),"—") -> Suministros Torres SA | C143: =IFERROR(LARGE($I$156:$I$193,A143),0) -> 265223.27 | D143: =IFERROR(SUMIFS(Ventas!$U$2:$U$1620,Ventas!$D$2:$D$1620,$B143,Ventas!$B$2:$B$1620,">="&$G$6,Ventas!$B$2:$B$1620,"<="&$G$7,Ventas!$E$2:$E$1620,$G$8,Ventas!$F$2:$F$1620,$H$8),0) -> 80529.702 | E143: =IFERROR(D143/C143,0) -> 0.30362986
A144: 7 | B144: =IFERROR(INDEX($H$156:$H$193,MATCH(LARGE($I$156:$I$193,A144),$I$156:$I$193,0)),"—") -> Grupo Ferretero Andalucía SA | C144: =IFERROR(LARGE($I$156:$I$193,A144),0) -> 263571.55 | D144: =IFERROR(SUMIFS(Ventas!$U$2:$U$1620,Ventas!$D$2:$D$1620,$B144,Ventas!$B$2:$B$1620,">="&$G$6,Ventas!$B$2:$B$1620,"<="&$G$7,Ventas!$E$2:$E$1620,$G$8,Ventas!$F$2:$F$1620,$H$8),0) -> 79923.799 | E144: =IFERROR(D144/C144,0) -> 0.30323379
A145: 8 | B145: =IFERROR(INDEX($H$156:$H$193,MATCH(LARGE($I$156:$I$193,A145),$I$156:$I$193,0)),"—") -> Distribuciones Metálicas Levante SL | C145: =IFERROR(LARGE($I$156:$I$193,A145),0) -> 249578.96 | D145: =IFERROR(SUMIFS(Ventas!$U$2:$U$1620,Ventas!$D$2:$D$1620,$B145,Ventas!$B$2:$B$1620,">="&$G$6,Ventas!$B$2:$B$1620,"<="&$G$7,Ventas!$E$2:$E$1620,$G$8,Ventas!$F$2:$F$1620,$H$8),0) -> 76627.565 | E145: =IFERROR(D145/C145,0) -> 0.30702734
A146: 9 | B146: =IFERROR(INDEX($H$156:$H$193,MATCH(LARGE($I$156:$I$193,A146),$I$156:$I$193,0)),"—") -> Stahlhandel Ruhr GmbH | C146: =IFERROR(LARGE($I$156:$I$193,A146),0) -> 236461.49 | D146: =IFERROR(SUMIFS(Ventas!$U$2:$U$1620,Ventas!$D$2:$D$1620,$B146,Ventas!$B$2:$B$1620,">="&$G$6,Ventas!$B$2:$B$1620,"<="&$G$7,Ventas!$E$2:$E$1620,$G$8,Ventas!$F$2:$F$1620,$H$8),0) -> 64314.104 | E146: =IFERROR(D146/C146,0) -> 0.27198553
A147: 10 | B147: =IFERROR(INDEX($H$156:$H$193,MATCH(LARGE($I$156:$I$193,A147),$I$156:$I$193,0)),"—") -> Groupe Boulonnerie Paris SAS | C147: =IFERROR(LARGE($I$156:$I$193,A147),0) -> 215208.77 | D147: =IFERROR(SUMIFS(Ventas!$U$2:$U$1620,Ventas!$D$2:$D$1620,$B147,Ventas!$B$2:$B$1620,">="&$G$6,Ventas!$B$2:$B$1620,"<="&$G$7,Ventas!$E$2:$E$1620,$G$8,Ventas!$F$2:$F$1620,$H$8),0) -> 60258.155 | E147: =IFERROR(D147/C147,0) -> 0.2799986
H154: Zona de cálculo auxiliar — no modificar
H156: =Clientes!$A$2 -> Ferretería Industrial Bierzo SL | I156: =SUMIFS(Ventas!$P$2:$P$1620,Ventas!$D$2:$D$1620,$H156,Ventas!$B$2:$B$1620,">="&$G$6,Ventas!$B$2:$B$1620,"<="&$G$7,Ventas!$E$2:$E$1620,$G$8,Ventas!$F$2:$F$1620,$H$8) -> 126441.11
H157: =Clientes!$A$3 -> Suministros Torres SA | I157: =SUMIFS(Ventas!$P$2:$P$1620,Ventas!$D$2:$D$1620,$H157,Ventas!$B$2:$B$1620,">="&$G$6,Ventas!$B$2:$B$1620,"<="&$G$7,Ventas!$E$2:$E$1620,$G$8,Ventas!$F$2:$F$1620,$H$8) -> 265223.27
H158: =Clientes!$A$4 -> Distribuciones Metálicas Levante SL | I158: =SUMIFS(Ventas!$P$2:$P$1620,Ventas!$D$2:$D$1620,$H158,Ventas!$B$2:$B$1620,">="&$G$6,Ventas!$B$2:$B$1620,"<="&$G$7,Ventas!$E$2:$E$1620,$G$8,Ventas!$F$2:$F$1620,$H$8) -> 249578.96
H159: =Clientes!$A$5 -> Construcciones Álvarez e Hijos SL | I159: =SUMIFS(Ventas!$P$2:$P$1620,Ventas!$D$2:$D$1620,$H159,Ventas!$B$2:$B$1620,">="&$G$6,Ventas!$B$2:$B$1620,"<="&$G$7,Ventas!$E$2:$E$1620,$G$8,Ventas!$F$2:$F$1620,$H$8) -> 205836.48
H160: =Clientes!$A$6 -> Aceros del Norte SA | I160: =SUMIFS(Ventas!$P$2:$P$1620,Ventas!$D$2:$D$1620,$H160,Ventas!$B$2:$B$1620,">="&$G$6,Ventas!$B$2:$B$1620,"<="&$G$7,Ventas!$E$2:$E$1620,$G$8,Ventas!$F$2:$F$1620,$H$8) -> 268007.9
H161: =Clientes!$A$7 -> Bricolaje Ponferrada SL | I161: =SUMIFS(Ventas!$P$2:$P$1620,Ventas!$D$2:$D$1620,$H161,Ventas!$B$2:$B$1620,">="&$G$6,Ventas!$B$2:$B$1620,"<="&$G$7,Ventas!$E$2:$E$1620,$G$8,Ventas!$F$2:$F$1620,$H$8) -> 133078.61
H162: =Clientes!$A$8 -> Montajes Industriales Vigo SL | I162: =SUMIFS(Ventas!$P$2:$P$1620,Ventas!$D$2:$D$1620,$H162,Ventas!$B$2:$B$1620,">="&$G$6,Ventas!$B$2:$B$1620,"<="&$G$7,Ventas!$E$2:$E$1620,$G$8,Ventas!$F$2:$F$1620,$H$8) -> 290874.72
H163: =Clientes!$A$9 -> Talleres Gómez Maquinaria SL | I163: =SUMIFS(Ventas!$P$2:$P$1620,Ventas!$D$2:$D$1620,$H163,Ventas!$B$2:$B$1620,">="&$G$6,Ventas!$B$2:$B$1620,"<="&$G$7,Ventas!$E$2:$E$1620,$G$8,Ventas!$F$2:$F$1620,$H$8) -> 124848.07
H164: =Clientes!$A$10 -> Suministros Ebro SL | I164: =SUMIFS(Ventas!$P$2:$P$1620,Ventas!$D$2:$D$1620,$H164,Ventas!$B$2:$B$1620,">="&$G$6,Ventas!$B$2:$B$1620,"<="&$G$7,Ventas!$E$2:$E$1620,$G$8,Ventas!$F$2:$F$1620,$H$8) -> 193539.61
H165: =Clientes!$A$11 -> Grupo Ferretero Andalucía SA | I165: =SUMIFS(Ventas!$P$2:$P$1620,Ventas!$D$2:$D$1620,$H165,Ventas!$B$2:$B$1620,">="&$G$6,Ventas!$B$2:$B$1620,"<="&$G$7,Ventas!$E$2:$E$1620,$G$8,Ventas!$F$2:$F$1620,$H$8) -> 263571.55
H166: =Clientes!$A$12 -> Naval Cádiz Servicios SA | I166: =SUMIFS(Ventas!$P$2:$P$1620,Ventas!$D$2:$D$1620,$H166,Ventas!$B$2:$B$1620,">="&$G$6,Ventas!$B$2:$B$1620,"<="&$G$7,Ventas!$E$2:$E$1620,$G$8,Ventas!$F$2:$F$1620,$H$8) -> 166170.89
H167: =Clientes!$A$13 -> Carpintería Roble Sur SL | I167: =SUMIFS(Ventas!$P$2:$P$1620,Ventas!$D$2:$D$1620,$H167,Ventas!$B$2:$B$1620,">="&$G$6,Ventas!$B$2:$B$1620,"<="&$G$7,Ventas!$E$2:$E$1620,$G$8,Ventas!$F$2:$F$1620,$H$8) -> 148026.53
H168: =Clientes!$A$14 -> Estructuras Duero SA | I168: =SUMIFS(Ventas!$P$2:$P$1620,Ventas!$D$2:$D$1620,$H168,Ventas!$B$2:$B$1620,">="&$G$6,Ventas!$B$2:$B$1620,"<="&$G$7,Ventas!$E$2:$E$1620,$G$8,Ventas!$F$2:$F$1620,$H$8) -> 171898.92
H169: =Clientes!$A$15 -> Herrajes Toledo SL | I169: =SUMIFS(Ventas!$P$2:$P$1620,Ventas!$D$2:$D$1620,$H169,Ventas!$B$2:$B$1620,">="&$G$6,Ventas!$B$2:$B$1620,"<="&$G$7,Ventas!$E$2:$E$1620,$G$8,Ventas!$F$2:$F$1620,$H$8) -> 91241.049
H170: =Clientes!$A$16 -> Almacenes Ibéricos de Tornillería SL | I170: =SUMIFS(Ventas!$P$2:$P$1620,Ventas!$D$2:$D$1620,$H170,Ventas!$B$2:$B$1620,">="&$G$6,Ventas!$B$2:$B$1620,"<="&$G$7,Ventas!$E$2:$E$1620,$G$8,Ventas!$F$2:$F$1620,$H$8) -> 195346.82
...

Sheet Instrucciones
A1: TORNILLERÍA BERCINOX, S.L. — Cuadro de control de ventas, costes y márgenes
A2: DATOS 100 % FICTICIOS, generados para pruebas. Ninguna cifra procede de una empresa real.
A4: Ficha del modelo
A5: Actividad | B5: Fabricación y distribución de tornillería industrial (métrica, inox, madera, autotaladrante)
A6: Mercados | B6: España, Alemania y Francia
A7: Periodo | B7: enero 2025 – junio 2026 (18 meses)
A8: Moneda | B8: Euros. Todos los importes son NETOS, sin IVA
A9: IVA / fiscalidad | B9: Ventas nacionales con IVA repercutido; ventas a Alemania y Francia como entrega intracomunitaria exenta (no se modela aquí)
A10: Unidad de venta | B10: Caja. Las unidades por caja están en la hoja Productos
A12: Hojas del libro
A13: Parametros | B13: Supuestos del modelo: comisiones, días de cobro, portes por país, coste del acero y objetivos mensuales
A14: Productos | B14: Maestro de artículos con coste base, precio de lista y resultados acumulados
A15: Clientes | B15: Maestro de clientes con ventas, margen, pedidos y saldo pendiente de cobro
A16: Ventas | B16: Detalle línea a línea de cada pedido. Es la base de datos del libro
A17: Gastos | B17: Gastos de explotación mensuales por categoría (fijos y variables)
A18: PL_Mensual | B18: Cuenta de resultados mensual: ingresos, coste de ventas, margen bruto, gastos y EBITDA
A19: KPIs | B19: Resúmenes por país, familia, canal, comercial, top clientes y situación de cobro
A21: Código de colores
A22: Azul | B22: Dato introducido a mano. Se puede modificar
A23: Negro | B23: Fórmula calculada dentro de la misma hoja. No tocar
A24: Verde | B24: Fórmula que enlaza con otra hoja del libro. No tocar
A25: Relleno amarillo | B25: Supuesto clave del modelo: cámbialo aquí y se propaga a todo el libro
A27: Cómo se usa
A28: 1 | B28: Para añadir ventas: inserta filas al final de la hoja Ventas y copia las fórmulas de la fila anterior (columnas C, I, J, M, O-V, W, Y).
A29: 2 | B29: Las columnas que se rellenan a mano en Ventas son: A pedido, B fecha, D cliente, E país, F canal, G comercial, H código, K tipo, L cajas, N descuento y X estado de cobro.
A30: 3 | B30: Ejemplo de fila válida: P-3000 | 15/07/2026 | Suministros Torres SA | España | Distribuidor | Alberto Ruiz | TOR-002 | Venta | 120 | 0,150 | Pendiente
A31: 4 | B31: Un abono se registra como tipo "Abono" con cajas en negativo. Resta ingresos y margen automáticamente.
A32: 5 | B32: Los rangos de las fórmulas resumen llegan hasta la fila 1620 de Ventas. Si añades más filas, amplía los rangos en PL_Mensual, KPIs, Clientes y Productos.
A33: 6 | B33: Recalcula el libro (F9) después de cambiar cualquier supuesto de Parametros.

Sheet Parametros
A1: PARÁMETROS Y SUPUESTOS DEL MODELO
A2: Celdas en azul con relleno amarillo = supuestos editables. Todo el libro se recalcula a partir de aquí.
A4: Datos generales
A5: Empresa | B5: Tornillería Bercinox, S.L. (ficticia)
A6: Actividad | B6: Fabricación y venta de tornillería industrial
A7: Moneda | B7: EUR — importes netos sin IVA
A8: Periodo del modelo | B8: ene-2025 a jun-2026
A9: Fecha de referencia | B9: 46233
A11: Comisión comercial y condiciones de cobro por canal
A12: Canal | B12: Comisión s/ venta | C12: Días de cobro
A13: Distribuidor | B13: 0.03 | C13: 60
A14: OEM / Industria | B14: 0.04 | C14: 75
A15: Ferretería | B15: 0.035 | C15: 45
A16: Ecommerce | B16: 0.01 | C16: 0
A18: Coste logístico por país
A19: País | B19: Portes €/caja | C19: Observaciones
A20: España | B20: 0.85 | C20: Transporte propio + agencia nacional
A21: Alemania | B21: 2.4 | C21: Grupaje internacional, entrega 4-6 días
A22: Francia | B22: 1.9 | C22: Grupaje internacional, entrega 3-5 días
A24: Índice de coste del acero y objetivo de ventas por mes
A25: Mes | B25: Factor coste acero | C25: Objetivo ventas netas
A26: 45658 | B26: 1.013 | C26: 300000
A27: 45689 | B27: 1.041 | C27: 340000
A28: 45717 | B28: 1.03 | C28: 380000
A29: 45748 | B29: 1.014 | C29: 380000
A30: 45778 | B30: 1.03 | C30: 375000
A31: 45809 | B31: 1.027 | C31: 385000
A32: 45839 | B32: 1.034 | C32: 360000
A33: 45870 | B33: 1.019 | C33: 250000
A34: 45901 | B34: 1.012 | C34: 340000
A35: 45931 | B35: 1.019 | C35: 370000
A36: 45962 | B36: 1.02 | C36: 390000
A37: 45992 | B37: 1.015 | C37: 360000
... A43: 46174 | B43: 1.008 | C43: 370000
A45: Notas de los supuestos
A46: • Factor coste acero: multiplica el coste base de cada artículo (hoja Productos) para reflejar la evolución del precio de la materia prima. 1,000 = coste base.
A47: • Portes: coste medio de transporte por caja expedida, imputado a cada línea de venta según el país de destino.
A48: • Comisión: se calcula sobre el ingreso neto de la línea, después de descuento.
A49: • Días de cobro: vencimiento teórico = fecha de pedido + días del canal. El estado real de cobro se informa a mano en la hoja Ventas.
A50: • Objetivo de ventas: cifra de presupuesto anual repartida por meses. Supuesto interno, no procede de ninguna fuente externa.
A51: • Todos los valores de esta hoja son inventados; no hay fuente externa que citar.

Sheet Productos
A1: Código | B1: Descripción | C1: Familia | D1: Uds/caja | E1: Coste base €/caja | F1: Precio lista €/caja | G1: Margen teórico % | H1: Cajas vendidas | I1: Ingresos netos | J1: Margen bruto € | K1: Margen % | L1: % s/ ventas
A2: TOR-001 | B2: Tornillo DIN 933 M6x30 rosca completa zincado | C2: Métrica | D2: 500 | E2: 16.6 | F2: 32 | G2: =IFERROR((F2-E2)/F2,0) -> 0.48125 | H2: =SUMIFS(Ventas!$L$2:$L$1620,Ventas!$H$2:$H$1620,$A2) -> 13487 | I2: =SUMIFS(Ventas!$P$2:$P$1620,Ventas!$H$2:$H$1620,$A2) -> 369121.47 | J2: =SUMIFS(Ventas!$U$2:$U$1620,Ventas!$H$2:$H$1620,$A2) -> 109209.73 | K2: =IFERROR(J2/I2,0) -> 0.29586393 | L2: =IFERROR(I2/$I$14,0) -> 0.0570548
A3: TOR-002 | B3: Tornillo DIN 933 M8x40 rosca completa zincado | C3: Métrica | D3: 250 | E3: 19.4 | F3: 37.5 | G3: =IFERROR((F3-E3)/F3,0) -> 0.48266667 | H3: =SUMIFS(Ventas!$L$2:$L$1620,Ventas!$H$2:$H$1620,$A3) -> 13362 | I3: =SUMIFS(Ventas!$P$2:$P$1620,Ventas!$H$2:$H$1620,$A3) -> 428897.44 | J3: =SUMIFS(Ventas!$U$2:$U$1620,Ventas!$H$2:$H$1620,$A3) -> 130678.52 | K3: =IFERROR(J3/I3,0) -> 0.30468477 | L3: =IFERROR(I3/$I$14,0) -> 0.066294321
A4: TOR-003 | B4: Tornillo DIN 912 M6x25 Allen zincado | C4: Métrica | D4: 500 | E4: 21.8 | F4: 42 | G4: =IFERROR((F4-E4)/F4,0) -> 0.48095238 | H4: =SUMIFS(Ventas!$L$2:$L$1620,Ventas!$H$2:$H$1620,$A4) -> 11699 | I4: =SUMIFS(Ventas!$P$2:$P$1620,Ventas!$H$2:$H$1620,$A4) -> 421242.99 | J4: =SUMIFS(Ventas!$U$2:$U$1620,Ventas!$H$2:$H$1620,$A4) -> 129140.73 | K4: =IFERROR(J4/I4,0) -> 0.30657064 | L4: =IFERROR(I4/$I$14,0) -> 0.06511118
A5: TOR-004 | B5: Tornillo DIN 912 M10x60 Allen inox A2 | C5: Inoxidable | D5: 100 | E5: 42 | F5: 79 | G5: =IFERROR((F5-E5)/F5,0) -> 0.46835443 | H5: =SUMIFS(Ventas!$L$2:$L$1620,Ventas!$H$2:$H$1620,$A5) -> 11987 | I5: =SUMIFS(Ventas!$P$2:$P$1620,Ventas!$H$2:$H$1620,$A5) -> 819582.34 | J5: =SUMIFS(Ventas!$U$2:$U$1620,Ventas!$H$2:$H$1620,$A5) -> 258905.9 | K5: =IFERROR(J5/I5,0) -> 0.3158998 | L5: =IFERROR(I5/$I$14,0) -> 0.12668216
A6: TOR-005 | B6: Tornillo DIN 7991 M8x30 avellanado inox A2 | C6: Inoxidable | D6: 200 | E6: 46.5 | F6: 88 | G6: =IFERROR((F6-E6)/F6,0) -> 0.47159091 | H6: =SUMIFS(Ventas!$L$2:$L$1620,Ventas!$H$2:$H$1620,$A6) -> 9755 | I6: =SUMIFS(Ventas!$P$2:$P$1620,Ventas!$H$2:$H$1620,$A6) -> 738066.21 | J6: =SUMIFS(Ventas!$U$2:$U$1620,Ventas!$H$2:$H$1620,$A6) -> 235645.44 | K6: =IFERROR(J6/I6,0) -> 0.31927412 | L6: =IFERROR(I6/$I$14,0) -> 0.11408228
A7: TOR-006 | B7: Tornillo DIN 933 M12x70 clase 8.8 | C7: Métrica | D7: 100 | E7: 33.5 | F7: 64 | G7: =IFERROR((F7-E7)/F7,0) -> 0.4765625 | H7: =SUMIFS(Ventas!$L$2:$L$1620,Ventas!$H$2:$H$1620,$A7) -> 12208 | I7: =SUMIFS(Ventas!$P$2:$P$1620,Ventas!$H$2:$H$1620,$A7) -> 665406.59 | J7: =SUMIFS(Ventas!$U$2:$U$1620,Ventas!$H$2:$H$1620,$A7) -> 208741.74 | K7: =IFERROR(J7/I7,0) -> 0.31370554 | L7: =IFERROR(I7/$I$14,0) -> 0.10285135
A8: TOR-007 | B8: Tirafondo madera 5x60 cabeza plana Torx | C8: Madera | D8: 500 | E8: 13.4 | F8: 26 | G8: =IFERROR((F8-E8)/F8,0) -> 0.48461538 | H8: =SUMIFS(Ventas!$L$2:$L$1620,Ventas!$H$2:$H$1620,$A8) -> 11094 | I8: =SUMIFS(Ventas!$P$2:$P$1620,Ventas!$H$2:$H$1620,$A8) -> 248299.09 | J8: =SUMIFS(Ventas!$U$2:$U$1620,Ventas!$H$2:$H$1620,$A8) -> 70315.581 | K8: =IFERROR(J8/I8,0) -> 0.28318904 | L8: =IFERROR(I8/$I$14,0) -> 0.038379384
A9: TOR-008 | B9: Tirafondo madera 6x100 cabeza plana Torx | C9: Madera | D9: 200 | E9: 17.8 | F9: 34 | G9: =IFERROR((F9-E9)/F9,0) -> 0.47647059 | H9: =SUMIFS(Ventas!$L$2:$L$1620,Ventas!$H$2:$H$1620,$A9) -> 12193 | I9: =SUMIFS(Ventas!$P$2:$P$1620,Ventas!$H$2:$H$1620,$A9) -> 351196.51 | J9: =SUMIFS(Ventas!$U$2:$U$1620,Ventas!$H$2:$H$1620,$A9) -> 99269.978 | K9: =IFERROR(J9/I9,0) -> 0.2826622 | L9: =IFERROR(I9/$I$14,0) -> 0.054284153
A10: TOR-009 | B10: Autotaladrante DIN 7504 4,8x38 zincado | C10: Autotaladrante | D10: 500 | E10: 15.2 | F10: 29.5 | G10: =IFERROR((F10-E10)/F10,0) -> 0.48474576 | H10: =SUMIFS(Ventas!$L$2:$L$1620,Ventas!$H$2:$H$1620,$A10) -> 11639 | I10: =SUMIFS(Ventas!$P$2:$P$1620,Ventas!$H$2:$H$1620,$A10) -> 295570.32 | J10: =SUMIFS(Ventas!$U$2:$U$1620,Ventas!$H$2:$H$1620,$A10) -> 88469.048 | K10: =IFERROR(J10/I10,0) -> 0.29931641 | L10: =IFERROR(I10/$I$14,0) -> 0.04568606
A11: TOR-010 | B11: Autotaladrante 5,5x55 punta broca | C11: Autotaladrante | D11: 250 | E11: 20.3 | F11: 39 | G11: =IFERROR((F11-E11)/F11,0) -> 0.47948718 | H11: =SUMIFS(Ventas!$L$2:$L$1620,Ventas!$H$2:$H$1620,$A11) -> 11802 | I11: =SUMIFS(Ventas!$P$2:$P$1620,Ventas!$H$2:$H$1620,$A11) -> 393928.2 | J11: =SUMIFS(Ventas!$U$2:$U$1620,Ventas!$H$2:$H$1620,$A11) -> 119737.12 | K11: =IFERROR(J11/I11,0) -> 0.3039567 | L11: =IFERROR(I11/$I$14,0) -> 0.060889155
A12: TOR-011 | B12: Tornillo estructural M16x90 clase 10.9 | C12: Especial | D12: 50 | E12: 60 | F12: 112 | G12: =IFERROR((F12-E12)/F12,0) -> 0.46428571 | H12: =SUMIFS(Ventas!$L$2:$L$1620,Ventas!$H$2:$H$1620,$A12) -> 12668 | I12: =SUMIFS(Ventas!$P$2:$P$1620,Ventas!$H$2:$H$1620,$A12) -> 1220648.7 | J12: =SUMIFS(Ventas!$U$2:$U$1620,Ventas!$H$2:$H$1620,$A12) -> 386774.87 | K12: =IFERROR(J12/I12,0) -> 0.31686011 | L12: =IFERROR(I12/$I$14,0) -> 0.18867466
A13: TOR-012 | B13: Varilla roscada M10 x 1 m zincada | C13: Especial | D13: 25 | E13: 28.5 | F13: 54 | G13: =IFERROR((F13-E13)/F13,0) -> 0.47222222 | H13: =SUMIFS(Ventas!$L$2:$L$1620,Ventas!$H$2:$H$1620,$A13) -> 11216 | I13: =SUMIFS(Ventas!$P$2:$P$1620,Ventas!$H$2:$H$1620,$A13) -> 517635.58 | J13: =SUMIFS(Ventas!$U$2:$U$1620,Ventas!$H$2:$H$1620,$A13) -> 157836.17 | K13: =IFERROR(J13/I13,0) -> 0.30491754 | L13: =IFERROR(I13/$I$14,0) -> 0.080010502
A14: TOTAL | H14: =SUM(H2:H13) -> 143110 | I14: =SUM(I2:I13) -> 6469595.4 | J14: =SUM(J2:J13) -> 1994724.8 | K14: =IFERROR(J14/I14,0) -> 0.30832296 | L14: =SUM(L2:L13) -> 1

Sheet Clientes
A1: Cliente | B1: País | C1: Canal | D1: Comercial asignado | E1: Cliente desde | F1: Ingresos netos | G1: Margen bruto € | H1: Margen % | I1: Nº pedidos | J1: Ticket medio | K1: Última compra | L1: Pendiente de cobro
A2: Ferretería Industrial Bierzo SL | B2: España | C2: Ferretería | D2: Alberto Ruiz | E2: 43815 | F2: =SUMIFS(Ventas!$P$2:$P$1620,Ventas!$D$2:$D$1620,$A2) -> 126441.11 | G2: =SUMIFS(Ventas!$U$2:$U$1620,Ventas!$D$2:$D$1620,$A2) -> 46502.205 | H2: =IFERROR(G2/F2,0) -> 0.36777756 | I2: =SUMIFS(Ventas!$Y$2:$Y$1620,Ventas!$D$2:$D$1620,$A2) -> 20 | J2: =IFERROR(F2/I2,0) -> 6322.0557 | K2: =_xlfn.MAXIFS(Ventas!$B$2:$B$1620,Ventas!$D$2:$D$1620,$A2) -> 46188 | L2: =SUMIFS(Ventas!$P$2:$P$1620,Ventas!$D$2:$D$1620,$A2,Ventas!$X$2:$X$1620,"Pendiente")+SUMIFS(Ventas!$P$2:$P$1620,Ventas!$D$2:$D$1620,$A2,Ventas!$X$2:$X$1620,"Vencido") -> 7201.571
A3: Suministros Torres SA | B3: España | C3: Distribuidor | D3: Alberto Ruiz | E3: 43923 | F3: =SUMIFS(Ventas!$P$2:$P$1620,Ventas!$D$2:$D$1620,$A3) -> 265223.27 | G3: =SUMIFS(Ventas!$U$2:$U$1620,Ventas!$D$2:$D$1620,$A3) -> 80529.702 | H3: =IFERROR(G3/F3,0) -> 0.30362986 | I3: =SUMIFS(Ventas!$Y$2:$Y$1620,Ventas!$D$2:$D$1620,$A3) -> 29 | J3: =IFERROR(F3/I3,0) -> 9145.6298 | K3: =_xlfn.MAXIFS(Ventas!$B$2:$B$1620,Ventas!$D$2:$D$1620,$A3) -> 46182 | L3: =SUMIFS(Ventas!$P$2:$P$1620,Ventas!$D$2:$D$1620,$A3,Ventas!$X$2:$X$1620,"Pendiente")+SUMIFS(Ventas!$P$2:$P$1620,Ventas!$D$2:$D$1620,$A3,Ventas!$X$2:$X$1620,"Vencido") -> 39261.903
A4: Distribuciones Metálicas Levante SL | B4: España | C4: Distribuidor | D4: Nuria Salas | E4: 45221 | F4: =SUMIFS(Ventas!$P$2:$P$1620,Ventas!$D$2:$D$1620,$A4) -> 249578.96 | G4: =SUMIFS(Ventas!$U$2:$U$1620,Ventas!$D$2:$D$1620,$A4) -> 76627.565 | H4: =IFERROR(G4/F4,0) -> 0.30702734 | I4: =SUMIFS(Ventas!$Y$2:$Y$1620,Ventas!$D$2:$D$1620,$A4) -> 33 | J4: =IFERROR(F4/I4,0) -> 7562.9988 | K4: =_xlfn.MAXIFS(Ventas!$B$2:$B$1620,Ventas!$D$2:$D$1620,$A4) -> 46195 | L4: =SUMIFS(Ventas!$P$2:$P$1620,Ventas!$D$2:$D$1620,$A4,Ventas!$X$2:$X$1620,"Pendiente")+SUMIFS(Ventas!$P$2:$P$1620,Ventas!$D$2:$D$1620,$A4,Ventas!$X$2:$X$1620,"Vencido") -> 24377.751
A5: Construcciones Álvarez e Hijos SL | B5: España | C5: OEM / Industria | D5: Alberto Ruiz | E5: 44579 | F5: =SUMIFS(Ventas!$P$2:$P$1620,Ventas!$D$2:$D$1620,$A5) -> 205836.48 | G5: =SUMIFS(Ventas!$U$2:$U$1620,Ventas!$D$2:$D$1620,$A5) -> 68540.253 | H5: =IFERROR(G5/F5,0) -> 0.33298399 | I5: =SUMIFS(Ventas!$Y$2:$Y$1620,Ventas!$D$2:$D$1620,$A5) -> 19 | J5: =IFERROR(F5/I5,0) -> 10833.499 | K5: =_xlfn.MAXIFS(Ventas!$B$2:$B$1620,Ventas!$D$2:$D$1620,$A5) -> 46202 | L5: =SUMIFS(Ventas!$P$2:$P$1620,Ventas!$D$2:$D$1620,$A5,Ventas!$X$2:$X$1620,"Pendiente")+SUMIFS(Ventas!$P$2:$P$1620,Ventas!$D$2:$D$1620,$A5,Ventas!$X$2:$X$1620,"Vencido") -> 43385.658
A6: Aceros del Norte SA | B6: España | C6: Distribuidor | D6: Alberto Ruiz | E6: 44596 | F6: =SUMIFS(Ventas!$P$2:$P$1620,Ventas!$D$2:$D$1620,$A6) -> 268007.9 | G6: =SUMIFS(Ventas!$U$2:$U$1620,Ventas!$D$2:$D$1620,$A6) -> 80096.429 | H6: =IFERROR(G6/F6,0) -> 0.29885846 | I6: =SUMIFS(Ventas!$Y$2:$Y$1620,Ventas!$D$2:$D$1620,$A6) -> 30 | J6: =IFERROR(F6/I6,0) -> 8933.5966 | K6: =_xlfn.MAXIFS(Ventas!$B$2:$B$1620,Ventas!$D$2:$D$1620,$A6) -> 46189 | L6: =SUMIFS(Ventas!$P$2:$P$1620,Ventas!$D$2:$D$1620,$A6,Ventas!$X$2:$X$1620,"Pendiente")+SUMIFS(Ventas!$P$2:$P$1620,Ventas!$D$2:$D$1620,$A6,Ventas!$X$2:$X$1620,"Vencido") -> 21557.422
A7: Bricolaje Ponferrada SL | B7: España | C7: Ferretería | D7: Alberto Ruiz | E7: 44391 | F7: =SUMIFS(Ventas!$P$2:$P$1620,Ventas!$D$2:$D$1620,$A7) -> 133078.61 | G7: =SUMIFS(Ventas!$U$2:$U$1620,Ventas!$D$2:$D$1620,$A7) -> 50405.058 | H7: =IFERROR(G7/F7,0) -> 0.37876152 | I7: =SUMIFS(Ventas!$Y$2:$Y$1620,Ventas!$D$2:$D$1620,$A7) -> 26 | J7: =IFERROR(F7/I7,0) -> 5118.4082 | K7: =_xlfn.MAXIFS(Ventas!$B$2:$B$1620,Ventas!$D$2:$D$1620,$A7) -> 46191 | L7: =SUMIFS(Ventas!$P$2:$P$1620,Ventas!$D$2:$D$1620,$A7,Ventas!$X$2:$X$1620,"Pendiente")+SUMIFS(Ventas!$P$2:$P$1620,Ventas!$D$2:$D$1620,$A7,Ventas!$X$2:$X$1620,"Vencido") -> 23024.984
A8: Montajes Industriales Vigo SL | B8: España | C8: OEM / Industria | D8: Alberto Ruiz | E8: 43310 | F8: =SUMIFS(Ventas!$P$2:$P$1620,Ventas!$D$2:$D$1620,$A8) -> 290874.72 | G8: =SUMIFS(Ventas!$U$2:$U$1620,Ventas!$D$2:$D$1620,$A8) -> 94487.013 | H8: =IFERROR(G8/F8,0) -> 0.32483748 | I8: =SUMIFS(Ventas!$Y$2:$Y$1620,Ventas!$D$2:$D$1620,$A8) -> 29 | J8: =IFERROR(F8/I8,0) -> 10030.163 | K8: =_xlfn.MAXIFS(Ventas!$B$2:$B$1620,Ventas!$D$2:$D$1620,$A8) -> 46195 | L8: =SUMIFS(Ventas!$P$2:$P$1620,Ventas!$D$2:$D$1620,$A8,Ventas!$X$2:$X$1620,"Pendiente")+SUMIFS(Ventas!$P$2:$P$1620,Ventas!$D$2:$D$1620,$A8,Ventas!$X$2:$X$1620,"Vencido") -> 30110.51
A9: Talleres Gómez Maquinaria SL | B9: España | C9: OEM / Industria | D9: Alberto Ruiz | E9: 44385 | F9: =SUMIFS(Ventas!$P$2:$P$1620,Ventas!$D$2:$D$1620,$A9) -> 124848.07 | G9: =SUMIFS(Ventas!$U$2:$U$1620,Ventas!$D$2:$D$1620,$A9) -> 40291.457 | H9: =IFERROR(G9/F9,0) -> 0.32272392 | I9: =SUMIFS(Ventas!$Y$2:$Y$1620,Ventas!$D$2:$D$1620,$A9) -> 17 | J9: =IFERROR(F9/I9,0) -> 7344.004 | K9: =_xlfn.MAXIFS(Ventas!$B$2:$B$1620,Ventas!$D$2:$D$1620,$A9) -> 46195 | L9: =SUMIFS(Ventas!$P$2:$P$1620,Ventas!$D$2:$D$1620,$A9,Ventas!$X$2:$X$1620,"Pendiente")+SUMIFS(Ventas!$P$2:$P$1620,Ventas!$D$2:$D$1620,$A9,Ventas!$X$2:$X$1620,"Vencido") -> 9872.304
A10: Suministros Ebro SL | B10: España | C10: Distribuidor | D10: Alberto Ruiz | E10: 45655 | F10: =SUMIFS(Ventas!$P$2:$P$1620,Ventas!$D$2:$D$1620,$A10) -> 193539.61 | G10: =SUMIFS(Ventas!$U$2:$U$1620,Ventas!$D$2:$D$1620,$A10) -> 58753.733 | H10: =IFERROR(G10/F10,0) -> 0.30357472 | I10: =SUMIFS(Ventas!$Y$2:$Y$1620,Ventas!$D$2:$D$1620,$A10) -> 29 | J10: =IFERROR(F10/I10,0) -> 6673.7796 | K10: =_xlfn.MAXIFS(Ventas!$B$2:$B$1620,Ventas!$D$2:$D$1620,$A10) -> 46190 | L10: =SUMIFS(Ventas!$P$2:$P$1620,Ventas!$D$2:$D$1620,$A10,Ventas!$X$2:$X$1620,"Pendiente")+SUMIFS(Ventas!$P$2:$P$1620,Ventas!$D$2:$D$1620,$A10,Ventas!$X$2:$X$1620,"Vencido") -> 38251.264
A11: Grupo Ferretero Andalucía SA | B11: España | C11: Distribuidor | D11: Nuria Salas | E11: 45584 | F11: =SUMIFS(Ventas!$P$2:$P$1620,Ventas!$D$2:$D$1620,$A11) -> 263571.55 | G11: =SUMIFS(Ventas!$U$2:$U$1620,Ventas!$D$2:$D$1620,$A11) -> 79923.799 | H11: =IFERROR(G11/F11,0) -> 0.30323379 | I11: =SUMIFS(Ventas!$Y$2:$Y$1620,Ventas!$D$2:$D$1620,$A11) -> 23 | J11: =IFERROR(F11/I11,0) -> 11459.633 | K11: =_xlfn.MAXIFS(Ventas!$B$2:$B$1620,Ventas!$D$2:$D$1620,$A11) -> 46202 | L11: =SUMIFS(Ventas!$P$2:$P$1620,Ventas!$D$2:$D$1620,$A11,Ventas!$X$2:$X$1620,"Pendiente")+SUMIFS(Ventas!$P$2:$P$1620,Ventas!$D$2:$D$1620,$A11,Ventas!$X$2:$X$1620,"Vencido") -> 34681.476
A12: Naval Cádiz Servicios SA | B12: España | C12: OEM / Industria | D12: Nuria Salas | E12: 42462 | F12: =SUMIFS(Ventas!$P$2:$P$1620,Ventas!$D$2:$D$1620,$A12) -> 166170.89 | G12: =SUMIFS(Ventas!$U$2:$U$1620,Ventas!$D$2:$D$1620,$A12) -> 54725.614 | H12: =IFERROR(G12/F12,0) -> 0.32933334 | I12: =SUMIFS(Ventas!$Y$2:$Y$1620,Ventas!$D$2:$D$1620,$A12) -> 23 | J12: =IFERROR(F12/I12,0) -> 7224.8212 | K12: =_xlfn.MAXIFS(Ventas!$B$2:$B$1620,Ventas!$D$2:$D$1620,$A12) -> 46188 | L12: =SUMIFS(Ventas!$P$2:$P$1620,Ventas!$D$2:$D$1620,$A12,Ventas!$X$2:$X$1620,"Pendiente")+SUMIFS(Ventas!$P$2:$P$1620,Ventas!$D$2:$D$1620,$A12,Ventas!$X$2:$X$1620,"Vencido") -> 29845.655
A13: Carpintería Roble Sur SL | B13: España | C13: OEM / Industria | D13: Nuria Salas | E13: 43210 | F13: =SUMIFS(Ventas!$P$2:$P$1620,Ventas!$D$2:$D$1620,$A13) -> 148026.53 | G13: =SUMIFS(Ventas!$U$2:$U$1620,Ventas!$D$2:$D$1620,$A13) -> 47098.574 | H13: =IFERROR(G13/F13,0) -> 0.31817658 | I13: =SUMIFS(Ventas!$Y$2:$Y$1620,Ventas!$D$2:$D$1620,$A13) -> 17 | J13: =IFERROR(F13/I13,0) -> 8707.4428 | K13: =_xlfn.MAXIFS(Ventas!$B$2:$B$1620,Ventas!$D$2:$D$1620,$A13) -> 46176 | L13: =SUMIFS(Ventas!$P$2:$P$1620,Ventas!$D$2:$D$1620,$A13,Ventas!$X$2:$X$1620,"Pendiente")+SUMIFS(Ventas!$P$2:$P$1620,Ventas!$D$2:$D$1620,$A13,Ventas!$X$2:$X$1620,"Vencido") -> 26975.388
... A39: Ets Moreau Quincaillerie SARL | B39: Francia | C39: Ferretería | D39: Camille Girard | E39: 44162 | F39: =SUMIFS(Ventas!$P$2:$P$1620,Ventas!$D$2:$D$1620,$A39) -> 104919.74 | G39: =SUMIFS(Ventas!$U$2:$U$1620,Ventas!$D$2:$D$1620,$A39) -> 36678.018 | H39: =IFERROR(G39/F39,0) -> 0.34958167 | I39: =SUMIFS(Ventas!$Y$2:$Y$1620,Ventas!$D$2:$D$1620,$A39) -> 19 | J39: =IFERROR(F39/I39,0) -> 5522.0916 | K39: =_xlfn.MAXIFS(Ventas!$B$2:$B$1620,Ventas!$D$2:$D$1620,$A39) -> 46195 | L39: =SUMIFS(Ventas!$P$2:$P$1620,Ventas!$D$2:$D$1620,$A39,Ventas!$X$2:$X$1620,"Pendiente")+SUMIFS(Ventas!$P$2:$P$1620,Ventas!$D$2:$D$1620,$A39,Ventas!$X$2:$X$1620,"Vencido") -> 10354.112
A40: TOTAL | F40: =SUM(F2:F39) -> 6469595.4 | G40: =SUM(G2:G39) -> 1994724.8 | H40: =IFERROR(G40/F40,0) -> 0.30832296 | I40: =SUM(I2:I39) -> 868 | J40: =IFERROR(F40/I40,0) -> 7453.4509 | L40: =SUM(L2:L39) -> 767517.94

Sheet Ventas
A1: Nº pedido | B1: Fecha | C1: Mes | D1: Cliente | E1: País | F1: Canal | G1: Comercial | H1: Código | I1: Producto | J1: Familia | K1: Tipo | L1: Cajas | M1: Precio lista | N1: Dto. % | O1: Precio neto | P1: Ingresos netos | Q1: Coste unit. fabricación | R1: Coste de ventas | S1: Portes | T1: Comisión | U1: Margen bruto | V1: Margen % | W1: Vto. cobro | X1: Estado cobro | Y1: Pedido único
A2: P-1001 | B2: 45660 | C2: =DATE(YEAR(B2),MONTH(B2),1) -> 45658 | D2: Quincaillerie Provence SAS | E2: Francia | F2: Ferretería | G2: Camille Girard | H2: TOR-011 | I2: =INDEX(Productos!$B$2:$B$13,MATCH($H2,Productos!$A$2:$A$13,0)) -> Tornillo estructural M16x90 clase 10.9 | J2: =INDEX(Productos!$C$2:$C$13,MATCH($H2,Productos!$A$2:$A$13,0)) -> Especial | K2: Venta | L2: 55 | M2: =INDEX(Productos!$F$2:$F$13,MATCH($H2,Productos!$A$2:$A$13,0)) -> 112 | N2: 0.091 | O2: =M2*(1-N2) -> 101.808 | P2: =L2*O2 -> 5599.44 | Q2: =INDEX(Productos!$E$2:$E$13,MATCH($H2,Productos!$A$2:$A$13,0))*INDEX(Parametros!$B$26:$B$43,MATCH($C2,Parametros!$A$26:$A$43,0)) -> 60.78 | R2: =L2*Q2 -> 3342.9 | S2: =L2*INDEX(Parametros!$B$20:$B$22,MATCH($E2,Parametros!$A$20:$A$22,0)) -> 104.5 | T2: =P2*INDEX(Parametros!$B$13:$B$16,MATCH($F2,Parametros!$A$13:$A$16,0)) -> 195.9804 | U2: =P2-R2-S2-T2 -> 1956.0596 | V2: =IFERROR(U2/P2,0) -> 0.34933129 | W2: =B2+INDEX(Parametros!$C$13:$C$16,MATCH($F2,Parametros!$A$13:$A$16,0)) -> 45705 | X2: Cobrado | Y2: =IF(COUNTIF($A$2:$A2,A2)=1,1,0) -> 1
A3: P-1001 | B3: 45660 | C3: =DATE(YEAR(B3),MONTH(B3),1) -> 45658 | D3: Quincaillerie Provence SAS | E3: Francia | F3: Ferretería | G3: Camille Girard | H3: TOR-001 | I3: =INDEX(Productos!$B$2:$B$13,MATCH($H3,Productos!$A$2:$A$13,0)) -> Tornillo DIN 933 M6x30 rosca completa zincado | J3: =INDEX(Productos!$C$2:$C$13,MATCH($H3,Productos!$A$2:$A$13,0)) -> Métrica | K3: Venta | L3: 174 | M3: =INDEX(Productos!$F$2:$F$13,MATCH($H3,Productos!$A$2:$A$13,0)) -> 32 | N3: 0.075 | O3: =M3*(1-N3) -> 29.6 | P3: =L3*O3 -> 5150.4 | Q3: =INDEX(Productos!$E$2:$E$13,MATCH($H3,Productos!$A$2:$A$13,0))*INDEX(Parametros!$B$26:$B$43,MATCH($C3,Parametros!$A$26:$A$43,0)) -> 16.8158 | R3: =L3*Q3 -> 2925.9492 | S3: =L3*INDEX(Parametros!$B$20:$B$22,MATCH($E3,Parametros!$A$20:$A$22,0)) -> 330.6 | T3: =P3*INDEX(Parametros!$B$13:$B$16,MATCH($F3,Parametros!$A$13:$A$16,0)) -> 180.264 | U3: =P3-R3-S3-T3 -> 1713.5868 | V3: =IFERROR(U3/P3,0) -> 0.33270946 | W3: =B3+INDEX(Parametros!$C$13:$C$16,MATCH($F3,Parametros!$A$13:$A$16,0)) -> 45705 | X3: Cobrado | Y3: =IF(COUNTIF($A$2:$A3,A3)=1,1,0) -> 0
A4: P-1001 | B4: 45660 | C4: =DATE(YEAR(B4),MONTH(B4),1) -> 45658 | D4: Quincaillerie Provence SAS | E4: Francia | F4: Ferretería | G4: Camille Girard | H4: TOR-012 | I4: =INDEX(Productos!$B$2:$B$13,MATCH($H4,Productos!$A$2:$A$13,0)) -> Varilla roscada M10 x 1 m zincada | J4: =INDEX(Productos!$C$2:$C$13,MATCH($H4,Productos!$A$2:$A$13,0)) -> Especial | K4: Venta | L4: 102 | M4: =INDEX(Productos!$F$2:$F$13,MATCH($H4,Productos!$A$2:$A$13,0)) -> 54 | N4: 0.091 | O4: =M4*(1-N4) -> 49.086 | P4: =L4*O4 -> 5006.772 | Q4: =INDEX(Productos!$E$2:$E$13,MATCH($H4,Productos!$A$2:$A$13,0))*INDEX(Parametros!$B$26:$B$43,MATCH($C4,Parametros!$A$26:$A$43,0)) -> 28.8705 | R4: =L4*Q4 -> 2944.791 | S4: =L4*INDEX(Parametros!$B$20:$B$22,MATCH($E4,Parametros!$A$20:$A$22,0)) -> 193.8 | T4: =P4*INDEX(Parametros!$B$13:$B$16,MATCH($F4,Parametros!$A$13:$A$16,0)) -> 175.23702 | U4: =P4-R4-S4-T4 -> 1692.944 | V4: =IFERROR(U4/P4,0) -> 0.33813083 | W4: =B4+INDEX(Parametros!$C$13:$C$16,MATCH($F4,Parametros!$A$13:$A$16,0)) -> 45705 | X4: Cobrado | Y4: =IF(COUNTIF($A$2:$A4,A4)=1,1,0) -> 0
A5: P-1002 | B5: 45663 | C5: =DATE(YEAR(B5),MONTH(B5),1) -> 45658 | D5: Métallerie Dupont SARL | E5: Francia | F5: OEM / Industria | G5: Camille Girard | H5: TOR-006 | I5: =INDEX(Productos!$B$2:$B$13,MATCH($H5,Productos!$A$2:$A$13,0)) -> Tornillo DIN 933 M12x70 clase 8.8 | J5: =INDEX(Productos!$C$2:$C$13,MATCH($H5,Productos!$A$2:$A$13,0)) -> Métrica | K5: Venta | L5: 110 | M5: =INDEX(Productos!$F$2:$F$13,MATCH($H5,Productos!$A$2:$A$13,0)) -> 64 | N5: 0.175 | O5: =M5*(1-N5) -> 52.8 | P5: =L5*O5 -> 5808 | Q5: =INDEX(Productos!$E$2:$E$13,MATCH($H5,Productos!$A$2:$A$13,0))*INDEX(Parametros!$B$26:$B$43,MATCH($C5,Parametros!$A$26:$A$43,0)) -> 33.9355 | R5: =L5*Q5 -> 3732.905 | S5: =L5*INDEX(Parametros!$B$20:$B$22,MATCH($E5,Parametros!$A$20:$A$22,0)) -> 209 | T5: =P5*INDEX(Parametros!$B$13:$B$16,MATCH($F5,Parametros!$A$13:$A$16,0)) -> 232.32 | U5: =P5-R5-S5-T5 -> 1633.775 | V5: =IFERROR(U5/P5,0) -> 0.28129735 | W5: =B5+INDEX(Parametros!$C$13:$C$16,MATCH($F5,Parametros!$A$13:$A$16,0)) -> 45738 | X5: Cobrado | Y5: =IF(COUNTIF($A$2:$A5,A5)=1,1,0) -> 1
A6: P-1002 | B6: 45663 | C6: =DATE(YEAR(B6),MONTH(B6),1) -> 45658 | D6: Métallerie Dupont SARL | E6: Francia | F6: OEM / Industria | G6: Camille Girard | H6: TOR-010 | I6: =INDEX(Productos!$B$2:$B$13,MATCH($H6,Productos!$A$2:$A$13,0)) -> Autotaladrante 5,5x55 punta broca | J6: =INDEX(Productos!$C$2:$C$13,MATCH($H6,Productos!$A$2:$A$13,0)) -> Autotaladrante | K6: Venta | L6: 88 | M6: =INDEX(Productos!$F$2:$F$13,MATCH($H6,Productos!$A$2:$A$13,0)) -> 39 | N6: 0.152 | O6: =M6*(1-N6) -> 33.072 | P6: =L6*O6 -> 2910.336 | Q6: =INDEX(Productos!$E$2:$E$13,MATCH($H6,Productos!$A$2:$A$13,0))*INDEX(Parametros!$B$26:$B$43,MATCH($C6,Parametros!$A$26:$A$43,0)) -> 20.5639 | R6: =L6*Q6 -> 1809.6232 | S6: =L6*INDEX(Parametros!$B$20:$B$22,MATCH($E6,Parametros!$A$20:$A$22,0)) -> 167.2 | T6: =P6*INDEX(Parametros!$B$13:$B$16,MATCH($F6,Parametros!$A$13:$A$16,0)) -> 116.41344 | U6: =P6-R6-S6-T6 -> 817.09936 | V6: =IFERROR(U6/P6,0) -> 0.28075774 | W6: =B6+INDEX(Parametros!$C$13:$C$16,MATCH($F6,Parametros!$A$13:$A$16,0)) -> 45738 | X6: Cobrado | Y6: =IF(COUNTIF($A$2:$A6,A6)=1,1,0) -> 0
A7: P-1002 | B7: 45663 | C7: =DATE(YEAR(B7),MONTH(B7),1) -> 45658 | D7: Métallerie Dupont SARL | E7: Francia | F7: OEM / Industria | G7: Camille Girard | H7: TOR-007 | I7: =INDEX(Productos!$B$2:$B$13,MATCH($H7,Productos!$A$2:$A$13,0)) -> Tirafondo madera 5x60 cabeza plana Torx | J7: =INDEX(Productos!$C$2:$C$13,MATCH($H7,Productos!$A$2:$A$13,0)) -> Madera | K7: Venta | L7: 84 | M7: =INDEX(Productos!$F$2:$F$13,MATCH($H7,Productos!$A$2:$A$13,0)) -> 26 | N7: 0.122 | O7: =M7*(1-N7) -> 22.828 | P7: =L7*O7 -> 1917.552 | Q7: =INDEX(Productos!$E$2:$E$13,MATCH($H7,Productos!$A$2:$A$13,0))*INDEX(Parametros!$B$26:$B$43,MATCH($C7,Parametros!$A$26:$A$43,0)) -> 13.5742 | R7: =L7*Q7 -> 1140.2328 | S7: =L7*INDEX(Parametros!$B$20:$B$22,MATCH($E7,Parametros!$A$20:$A$22,0)) -> 159.6 | T7: =P7*INDEX(Parametros!$B$13:$B$16,MATCH($F7,Parametros!$A$13:$A$16,0)) -> 76.70208 | U7: =P7-R7-S7-T7 -> 541.01712 | V7: =IFERROR(U7/P7,0) -> 0.28213948 | W7: =B7+INDEX(Parametros!$C$13:$C$16,MATCH($F7,Parametros!$A$13:$A$16,0)) -> 45738 | X7: Cobrado | Y7: =IF(COUNTIF($A$2:$A7,A7)=1,1,0) -> 0
A8: P-1003 | B8: 45663 | C8: =DATE(YEAR(B8),MONTH(B8),1) -> 45658 | D8: Almacenes Ibéricos de Tornillería SL | E8: España | F8: Distribuidor | G8: Nuria Salas | H8: TOR-011 | I8: =INDEX(Productos!$B$2:$B$13,MATCH($H8,Productos!$A$2:$A$13,0)) -> Tornillo estructural M16x90 clase 10.9 | J8: =INDEX(Productos!$C$2:$C$13,MATCH($H8,Productos!$A$2:$A$13,0)) -> Especial | K8: Venta | L8: 60 | M8: =INDEX(Productos!$F$2:$F$13,MATCH($H8,Productos!$A$2:$A$13,0)) -> 112 | N8: 0.17 | O8: =M8*(1-N8) -> 92.96 | P8: =L8*O8 -> 5577.6 | Q8: =INDEX(Productos!$E$2:$E$13,MATCH($H8,Productos!$A$2:$A$13,0))*INDEX(Parametros!$B$26:$B$43,MATCH($C8,Parametros!$A$26:$A$43,0)) -> 60.78 | R8: =L8*Q8 -> 3646.8 | S8: =L8*INDEX(Parametros!$B$20:$B$22,MATCH($E8,Parametros!$A$20:$A$22,0)) -> 51 | T8: =P8*INDEX(Parametros!$B$13:$B$16,MATCH($F8,Parametros!$A$13:$A$16,0)) -> 167.328 | U8: =P8-R8-S8-T8 -> 1712.472 | V8: =IFERROR(U8/P8,0) -> 0.30702668 | W8: =B8+INDEX(Parametros!$C$13:$C$16,MATCH($F8,Parametros!$A$13:$A$16,0)) -> 45723 | X8: Cobrado | Y8: =IF(COUNTIF($A$2:$A8,A8)=1,1,0) -> 1
A9: P-1003 | B9: 45663 | C9: =DATE(YEAR(B9),MONTH(B9),1) -> 45658 | D9: Almacenes Ibéricos de Tornillería SL | E9: España | F9: Distribuidor | G9: Nuria Salas | H9: TOR-002 | I9: =INDEX(Productos!$B$2:$B$13,MATCH($H9,Productos!$A$2:$A$13,0)) -> Tornillo DIN 933 M8x40 rosca completa zincado | J9: =INDEX(Productos!$C$2:$C$13,MATCH($H9,Productos!$A$2:$A$13,0)) -> Métrica | K9: Venta | L9: 118 | M9: =INDEX(Productos!$F$2:$F$13,MATCH($H9,Productos!$A$2:$A$13,0)) -> 37.5 | N9: 0.134 | O9: =M9*(1-N9) -> 32.475 | P9: =L9*O9 -> 3832.05 | Q9: =INDEX(Productos!$E$2:$E$13,MATCH($H9,Productos!$A$2:$A$13,0))*INDEX(Parametros!$B$26:$B$43,MATCH($C9,Parametros!$A$26:$A$43,0)) -> 19.6522 | R9: =L9*Q9 -> 2318.9596 | S9: =L9*INDEX(Parametros!$B$20:$B$22,MATCH($E9,Parametros!$A$20:$A$22,0)) -> 100.3 | T9: =P9*INDEX(Parametros!$B$13:$B$16,MATCH($F9,Parametros!$A$13:$A$16,0)) -> 114.9615 | U9: =P9-R9-S9-T9 -> 1297.8289 | V9: =IFERROR(U9/P9,0) -> 0.33867744 | W9: =B9+INDEX(Parametros!$C$13:$C$16,MATCH($F9,Parametros!$A$13:$A$16,0)) -> 45723 | X9: Cobrado | Y9: =IF(COUNTIF($A$2:$A9,A9)=1,1,0) -> 0
A10: P-1004 | B10: 45663 | C10: =DATE(YEAR(B10),MONTH(B10),1) -> 45658 | D10: Schrauben Nord GmbH | E10: Alemania | F10: Distribuidor | G10: Klaus Berger | H10: TOR-005 | I10: =INDEX(Productos!$B$2:$B$13,MATCH($H10,Productos!$A$2:$A$13,0)) -> Tornillo DIN 7991 M8x30 avellanado inox A2 | J10: =INDEX(Productos!$C$2:$C$13,MATCH($H10,Productos!$A$2:$A$13,0)) -> Inoxidable | K10: Venta | L10: 58 | M10: =INDEX(Productos!$F$2:$F$13,MATCH($H10,Productos!$A$2:$A$13,0)) -> 88 | N10: 0.124 | O10: =M10*(1-N10) -> 77.088 | P10: =L10*O10 -> 4471.104 | Q10: =INDEX(Productos!$E$2:$E$13,MATCH($H10,Productos!$A$2:$A$13,0))*INDEX(Parametros!$B$26:$B$43,MATCH($C10,Parametros!$A$26:$A$43,0)) -> 47.1045 | R10: =L10*Q10 -> 2732.061 | S10: =L10*INDEX(Parametros!$B$20:$B$22,MATCH($E10,Parametros!$A$20:$A$22,0)) -> 139.2 | T10: =P10*INDEX(Parametros!$B$13:$B$16,MATCH($F10,Parametros!$A$13:$A$16,0)) -> 134.13312 | U10: =P10-R10-S10-T10 -> 1465.7099 | V10: =IFERROR(U10/P10,0) -> 0.32781834 | W10: =B10+INDEX(Parametros!$C$13:$C$16,MATCH($F10,Parametros!$A$13:$A$16,0)) -> 45723 | X10: Cobrado | Y10: =IF(COUNTIF($A$2:$A10,A10)=1,1,0) -> 1
A11: P-1004 | B11: 45663 | C11: =DATE(YEAR(B11),MONTH(B11),1) -> 45658 | D11: Schrauben Nord GmbH | E11: Alemania | F11: Distribuidor | G11: Klaus Berger | H11: TOR-011 | I11: =INDEX(Productos!$B$2:$B$13,MATCH($H11,Productos!$A$2:$A$13,0)) -> Tornillo estructural M16x90 clase 10.9 | J11: =INDEX(Productos!$C$2:$C$13,MATCH($H11,Productos!$A$2:$A$13,0)) -> Especial | K11: Venta | L11: 29 | M11: =INDEX(Productos!$F$2:$F$13,MATCH($H11,Productos!$A$2:$A$13,0)) -> 112 | N11: 0.152 | O11: =M11*(1-N11) -> 94.976 | P11: =L11*O11 -> 2754.304 | Q11: =INDEX(Productos!$E$2:$E$13,MATCH($H11,Productos!$A$2:$A$13,0))*INDEX(Parametros!$B$26:$B$43,MATCH($C11,Parametros!$A$26:$A$43,0)) -> 60.78 | R11: =L11*Q11 -> 1762.62 | S11: =L11*INDEX(Parametros!$B$20:$B$22,MATCH($E11,Parametros!$A$20:$A$22,0)) -> 69.6 | T11: =P11*INDEX(Parametros!$B$13:$B$16,MATCH($F11,Parametros!$A$13:$A$16,0)) -> 82.62912 | U11: =P11-R11-S11-T11 -> 839.45488 | V11: =IFERROR(U11/P11,0) -> 0.30477931 | W11: =B11+INDEX(Parametros!$C$13:$C$16,MATCH($F11,Parametros!$A$13:$A$16,0)) -> 45723 | X11: Cobrado | Y11: =IF(COUNTIF($A$2:$A11,A11)=1,1,0) -> 0
A12: P-1005 | B12: 45665 | C12: =DATE(YEAR(B12),MONTH(B12),1) -> 45658 | D12: Aceros del Norte SA | E12: España | F12: Distribuidor | G12: Alberto Ruiz | H12: TOR-010 | I12: =INDEX(Productos!$B$2:$B$13,MATCH($H12,Productos!$A$2:$A$13,0)) -> Autotaladrante 5,5x55 punta broca | J12: =INDEX(Productos!$C$2:$C$13,MATCH($H12,Productos!$A$2:$A$13,0)) -> Autotaladrante | K12: Venta | L12: 60 | M12: =INDEX(Productos!$F$2:$F$13,MATCH($H12,Productos!$A$2:$A$13,0)) -> 39 | N12: 0.183 | O12: =M12*(1-N12) -> 31.863 | P12: =L12*O12 -> 1911.78 | Q12: =INDEX(Productos!$E$2:$E$13,MATCH($H12,Productos!$A$2:$A$13,0))*INDEX(Parametros!$B$26:$B$43,MATCH($C12,Parametros!$A$26:$A$43,0)) -> 20.5639 | R12: =L12*Q12 -> 1233.834 | S12: =L12*INDEX(Parametros!$B$20:$B$22,MATCH($E12,Parametros!$A$20:$A$22,0)) -> 51 | T12: =P12*INDEX(Parametros!$B$13:$B$16,MATCH($F12,Parametros!$A$13:$A$16,0)) -> 57.3534 | U12: =P12-R12-S12-T12 -> 569.5926 | V12: =IFERROR(U12/P12,0) -> 0.29793836 | W12: =B12+INDEX(Parametros!$C$13:$C$16,MATCH($F12,Parametros!$A$13:$A$16,0)) -> 45725 | X12: Cobrado | Y12: =IF(COUNTIF($A$2:$A12,A12)=1,1,0) -> 1
A13: P-1006 | B13: 45665 | C13: =DATE(YEAR(B13),MONTH(B13),1) -> 45658 | D13: Aceros del Norte SA | E13: España | F13: Distribuidor | G13: Alberto Ruiz | H13: TOR-002 | I13: =INDEX(Productos!$B$2:$B$13,MATCH($H13,Productos!$A$2:$A$13,0)) -> Tornillo DIN 933 M8x40 rosca completa zincado | J13: =INDEX(Productos!$C$2:$C$13,MATCH($H13,Productos!$A$2:$A$13,0)) -> Métrica | K13: Venta | L13: 270 | M13: =INDEX(Productos!$F$2:$F$13,MATCH($H13,Productos!$A$2:$A$13,0)) -> 37.5 | N13: 0.157 | O13: =M13*(1-N13) -> 31.6125 | P13: =L13*O13 -> 8535.375 | Q13: =INDEX(Productos!$E$2:$E$13,MATCH($H13,Productos!$A$2:$A$13,0))*INDEX(Parametros!$B$26:$B$43,MATCH($C13,Parametros!$A$26:$A$43,0)) -> 19.6522 | R13: =L13*Q13 -> 5306.094 | S13: =L13*INDEX(Parametros!$B$20:$B$22,MATCH($E13,Parametros!$A$20:$A$22,0)) -> 229.5 | T13: =P13*INDEX(Parametros!$B$13:$B$16,MATCH($F13,Parametros!$A$13:$A$16,0)) -> 256.06125 | U13: =P13-R13-S13-T13 -> 2743.7198 | V13: =IFERROR(U13/P13,0) -> 0.32145275 | W13: =B13+INDEX(Parametros!$C$13:$C$16,MATCH($F13,Parametros!$A$13:$A$16,0)) -> 45725 | X13: Cobrado | Y13: =IF(COUNTIF($A$2:$A13,A13)=1,1,0) -> 1
... A1620: P-1868 | B1620: 46202 | C1620: =DATE(YEAR(B1620),MONTH(B1620),1) -> 46174 | D1620: Grupo Ferretero Andalucía SA | E1620: España | F1620: Distribuidor | G1620: Nuria Salas | H1620: TOR-003 | I1620: =INDEX(Productos!$B$2:$B$13,MATCH($H1620,Productos!$A$2:$A$13,0)) -> Tornillo DIN 912 M6x25 Allen zincado | J1620: =INDEX(Productos!$C$2:$C$13,MATCH($H1620,Productos!$A$2:$A$13,0)) -> Métrica | K1620: Venta | L1620: 41 | M1620: =INDEX(Productos!$F$2:$F$13,MATCH($H1620,Productos!$A$2:$A$13,0)) -> 42 | N1620: 0.196 | O1620: =M1620*(1-N1620) -> 33.768 | P1620: =L1620*O1620 -> 1384.488 | Q1620: =INDEX(Productos!$E$2:$E$13,MATCH($H1620,Productos!$A$2:$A$13,0))*INDEX(Parametros!$B$26:$B$43,MATCH($C1620,Parametros!$A$26:$A$43,0)) -> 21.9744 | R1620: =L1620*Q1620 -> 900.9504 | S1620: =L1620*INDEX(Parametros!$B$20:$B$22,MATCH($E1620,Parametros!$A$20:$A$22,0)) -> 34.85 | T1620: =P1620*INDEX(Parametros!$B$13:$B$16,MATCH($F1620,Parametros!$A$13:$A$16,0)) -> 41.53464 | U1620: =P1620-R1620-S1620-T1620 -> 407.15296 | V1620: =IFERROR(U1620/P1620,0) -> 0.29408197 | W1620: =B1620+INDEX(Parametros!$C$13:$C$16,MATCH($F1620,Parametros!$A$13:$A$16,0)) -> 46262 | X1620: Pendiente | Y1620: =IF(COUNTIF($A$2:$A1620,A1620)=1,1,0) -> 0

Sheet Gastos
A1: Mes | B1: Categoría | C1: Tipo | D1: Importe
A2: 45658 | B2: Nóminas producción | C2: Fijo | D2: 39801.04
A3: 45658 | B3: Nóminas estructura y comercial | C3: Fijo | D3: 18930.11
A4: 45658 | B4: Alquiler nave y oficinas | C4: Fijo | D4: 6500
A5: 45658 | B5: Energía y suministros | C5: Variable | D5: 11668.43
A6: 45658 | B6: Mantenimiento y utillaje maquinaria | C6: Variable | D6: 2312.82
A7: 45658 | B7: Marketing y acciones comerciales | C7: Variable | D7: 3053.19
A8: 45658 | B8: Software, ERP e IT | C8: Fijo | D8: 1197.55
A9: 45658 | B9: Asesoría, auditoría y legal | C9: Fijo | D9: 1266.56
A10: 45658 | B10: Seguros y tributos locales | C10: Fijo | D10: 1525.5
A11: 45658 | B11: Transporte no imputado a pedido | C11: Variable | D11: 2269.47
A12: 45658 | B12: Viajes y dietas comerciales | C12: Variable | D12: 2351.38
A13: 45658 | B13: Otros gastos de explotación | C13: Variable | D13: 1070.41
... A217: 46174 | B217: Otros gastos de explotación | C217: Variable | D217: 1588.36
A218: TOTAL | D218: =SUM(D2:D217) -> 1660812.6

Sheet PL_Mensual
A1: CUENTA DE RESULTADOS MENSUAL
A2: Ingresos y costes desde la hoja Ventas; gastos de explotación desde la hoja Gastos. Importes netos sin IVA.
A4: Mes | B4: Ingresos netos | C4: Coste de ventas | D4: Portes | E4: Comisiones | F4: Margen bruto | G4: Margen % | H4: Gastos fijos | I4: Gastos variables | J4: Total gastos explotación | K4: EBITDA | L4: EBITDA % | M4: Objetivo ventas | N4: Cumplimiento | O4: Nº pedidos | P4: Ticket medio
A5: =Parametros!$A$26 -> 45658 | B5: =SUMIFS(Ventas!$P$2:$P$1620,Ventas!$C$2:$C$1620,$A5) -> 211137.89 | C5: =SUMIFS(Ventas!$R$2:$R$1620,Ventas!$C$2:$C$1620,$A5) -> 129832.97 | D5: =SUMIFS(Ventas!$S$2:$S$1620,Ventas!$C$2:$C$1620,$A5) -> 7632.1 | E5: =SUMIFS(Ventas!$T$2:$T$1620,Ventas!$C$2:$C$1620,$A5) -> 7424.076 | F5: =B5-C5-D5-E5 -> 66248.749 | G5: =IFERROR(F5/B5,0) -> 0.31377006 | H5: =SUMIFS(Gastos!$D$2:$D$217,Gastos!$A$2:$A$217,$A5,Gastos!$C$2:$C$217,"Fijo") -> 69220.76 | I5: =SUMIFS(Gastos!$D$2:$D$217,Gastos!$A$2:$A$217,$A5,Gastos!$C$2:$C$217,"Variable") -> 22725.7 | J5: =H5+I5 -> 91946.46 | K5: =F5-J5 -> -25697.711 | L5: =IFERROR(K5/B5,0) -> -0.12171056 | M5: =INDEX(Parametros!$C$26:$C$43,MATCH($A5,Parametros!$A$26:$A$43,0)) -> 300000 | N5: =IFERROR(B5/M5,0) -> 0.70379298 | O5: =SUMIFS(Ventas!$Y$2:$Y$1620,Ventas!$C$2:$C$1620,$A5) -> 40 | P5: =IFERROR(B5/O5,0) -> 5278.4473
A6: =Parametros!$A$27 -> 45689 | B6: =SUMIFS(Ventas!$P$2:$P$1620,Ventas!$C$2:$C$1620,$A6) -> 359815.02 | C6: =SUMIFS(Ventas!$R$2:$R$1620,Ventas!$C$2:$C$1620,$A6) -> 229647.83 | D6: =SUMIFS(Ventas!$S$2:$S$1620,Ventas!$C$2:$C$1620,$A6) -> 11041.2 | E6: =SUMIFS(Ventas!$T$2:$T$1620,Ventas!$C$2:$C$1620,$A6) -> 11825.45 | F6: =B6-C6-D6-E6 -> 107300.54 | G6: =IFERROR(F6/B6,0) -> 0.2982103 | H6: =SUMIFS(Gastos!$D$2:$D$217,Gastos!$A$2:$A$217,$A6,Gastos!$C$2:$C$217,"Fijo") -> 68445.54 | I6: =SUMIFS(Gastos!$D$2:$D$217,Gastos!$A$2:$A$217,$A6,Gastos!$C$2:$C$217,"Variable") -> 27753.95 | J6: =H6+I6 -> 96199.49 | K6: =F6-J6 -> 11101.054 | L6: =IFERROR(K6/B6,0) -> 0.030852113 | M6: =INDEX(Parametros!$C$26:$C$43,MATCH($A6,Parametros!$A$26:$A$43,0)) -> 340000 | N6: =IFERROR(B6/M6,0) -> 1.0582795 | O6: =SUMIFS(Ventas!$Y$2:$Y$1620,Ventas!$C$2:$C$1620,$A6) -> 47 | P6: =IFERROR(B6/O6,0) -> 7655.6387
A7: =Parametros!$A$28 -> 45717 | B7: =SUMIFS(Ventas!$P$2:$P$1620,Ventas!$C$2:$C$1620,$A7) -> 402755.5 | C7: =SUMIFS(Ventas!$R$2:$R$1620,Ventas!$C$2:$C$1620,$A7) -> 253474.76 | D7: =SUMIFS(Ventas!$S$2:$S$1620,Ventas!$C$2:$C$1620,$A7) -> 13067 | E7: =SUMIFS(Ventas!$T$2:$T$1620,Ventas!$C$2:$C$1620,$A7) -> 13693.669 | F7: =B7-C7-D7-E7 -> 122520.07 | G7: =IFERROR(F7/B7,0) -> 0.30420458 | H7: =SUMIFS(Gastos!$D$2:$D$217,Gastos!$A$2:$A$217,$A7,Gastos!$C$2:$C$217,"Fijo") -> 68763.5 | I7: =SUMIFS(Gastos!$D$2:$D$217,Gastos!$A$2:$A$217,$A7,Gastos!$C$2:$C$217,"Variable") -> 21239.97 | J7: =H7+I7 -> 90003.47 | K7: =F7-J7 -> 32516.598 | L7: =IFERROR(K7/B7,0) -> 0.08073533 | M7: =INDEX(Parametros!$C$26:$C$43,MATCH($A7,Parametros!$A$26:$A$43,0)) -> 380000 | N7: =IFERROR(B7/M7,0) -> 1.0598829 | O7: =SUMIFS(Ventas!$Y$2:$Y$1620,Ventas!$C$2:$C$1620,$A7) -> 52 | P7: =IFERROR(B7/O7,0) -> 7745.298
A8: =Parametros!$A$29 -> 45748 | B8: =SUMIFS(Ventas!$P$2:$P$1620,Ventas!$C$2:$C$1620,$A8) -> 386160.31 | C8: =SUMIFS(Ventas!$R$2:$R$1620,Ventas!$C$2:$C$1620,$A8) -> 242561.07 | D8: =SUMIFS(Ventas!$S$2:$S$1620,Ventas!$C$2:$C$1620,$A8) -> 14308.5 | E8: =SUMIFS(Ventas!$T$2:$T$1620,Ventas!$C$2:$C$1620,$A8) -> 12744.32 | F8: =B8-C8-D8-E8 -> 116546.42 | G8: =IFERROR(F8/B8,0) -> 0.30180839 | H8: =SUMIFS(Gastos!$D$2:$D$217,Gastos!$A$2:$A$217,$A8,Gastos!$C$2:$C$217,"Fijo") -> 67546.83 | I8: =SUMIFS(Gastos!$D$2:$D$217,Gastos!$A$2:$A$217,$A8,Gastos!$C$2:$C$217,"Variable") -> 23423.83 | J8: =H8+I8 -> 90970.66 | K8: =F8-J8 -> 25575.762 | L8: =IFERROR(K8/B8,0) -> 0.066230945 | M8: =INDEX(Parametros!$C$26:$C$43,MATCH($A8,Parametros!$A$26:$A$43,0)) -> 380000 | N8: =IFERROR(B8/M8,0) -> 1.0162113 | O8: =SUMIFS(Ventas!$Y$2:$Y$1620,Ventas!$C$2:$C$1620,$A8) -> 49 | P8: =IFERROR(B8/O8,0) -> 7880.8227
A9: =Parametros!$A$30 -> 45778 | B9: =SUMIFS(Ventas!$P$2:$P$1620,Ventas!$C$2:$C$1620,$A9) -> 366914.69 | C9: =SUMIFS(Ventas!$R$2:$R$1620,Ventas!$C$2:$C$1620,$A9) -> 227267.65 | D9: =SUMIFS(Ventas!$S$2:$S$1620,Ventas!$C$2:$C$1620,$A9) -> 11300 | E9: =SUMIFS(Ventas!$T$2:$T$1620,Ventas!$C$2:$C$1620,$A9) -> 12704.733 | F9: =B9-C9-D9-E9 -> 115642.31 | G9: =IFERROR(F9/B9,0) -> 0.31517493 | H9: =SUMIFS(Gastos!$D$2:$D$217,Gastos!$A$2:$A$217,$A9,Gastos!$C$2:$C$217,"Fijo") -> 68844.1 | I9: =SUMIFS(Gastos!$D$2:$D$217,Gastos!$A$2:$A$217,$A9,Gastos!$C$2:$C$217,"Variable") -> 19254.17 | J9: =H9+I9 -> 88098.27 | K9: =F9-J9 -> 27544.04 | L9: =IFERROR(K9/B9,0) -> 0.075069331 | M9: =INDEX(Parametros!$C$26:$C$43,MATCH($A9,Parametros!$A$26:$A$43,0)) -> 375000 | N9: =IFERROR(B9/M9,0) -> 0.97843917 | O9: =SUMIFS(Ventas!$Y$2:$Y$1620,Ventas!$C$2:$C$1620,$A9) -> 55 | P9: =IFERROR(B9/O9,0) -> 6671.1762
A10: =Parametros!$A$31 -> 45809 | B10: =SUMIFS(Ventas!$P$2:$P$1620,Ventas!$C$2:$C$1620,$A10) -> 401613.7 | C10: =SUMIFS(Ventas!$R$2:$R$1620,Ventas!$C$2:$C$1620,$A10) -> 252763.6 | D10: =SUMIFS(Ventas!$S$2:$S$1620,Ventas!$C$2:$C$1620,$A10) -> 11005.4 | E10: =SUMIFS(Ventas!$T$2:$T$1620,Ventas!$C$2:$C$1620,$A10) -> 13449.824 | F10: =B10-C10-D10-E10 -> 124394.88 | G10: =IFERROR(F10/B10,0) -> 0.30973764 | H10: =SUMIFS(Gastos!$D$2:$D$217,Gastos!$A$2:$A$217,$A10,Gastos!$C$2:$C$217,"Fijo") -> 66898.41 | I10: =SUMIFS(Gastos!$D$2:$D$217,Gastos!$A$2:$A$217,$A10,Gastos!$C$2:$C$217,"Variable") -> 20739.01 | J10: =H10+I10 -> 87637.42 | K10: =F10-J10 -> 36757.462 | L10: =IFERROR(K10/B10,0) -> 0.091524422 | M10: =INDEX(Parametros!$C$26:$C$43,MATCH($A10,Parametros!$A$26:$A$43,0)) -> 385000 | N10: =IFERROR(B10/M10,0) -> 1.0431525 | O10: =SUMIFS(Ventas!$Y$2:$Y$1620,Ventas!$C$2:$C$1620,$A10) -> 48 | P10: =IFERROR(B10/O10,0) -> 8366.9521
A11: =Parametros!$A$32 -> 45839 | B11: =SUMIFS(Ventas!$P$2:$P$1620,Ventas!$C$2:$C$1620,$A11) -> 369003.3 | C11: =SUMIFS(Ventas!$R$2:$R$1620,Ventas!$C$2:$C$1620,$A11) -> 235061.29 | D11: =SUMIFS(Ventas!$S$2:$S$1620,Ventas!$C$2:$C$1620,$A11) -> 9233.2 | E11: =SUMIFS(Ventas!$T$2:$T$1620,Ventas!$C$2:$C$1620,$A11) -> 12875.322 | F11: =B11-C11-D11-E11 -> 111833.49 | G11: =IFERROR(F11/B11,0) -> 0.30306908 | H11: =SUMIFS(Gastos!$D$2:$D$217,Gastos!$A$2:$A$217,$A11,Gastos!$C$2:$C$217,"Fijo") -> 70297.9 | I11: =SUMIFS(Gastos!$D$2:$D$217,Gastos!$A$2:$A$217,$A11,Gastos!$C$2:$C$217,"Variable") -> 22939.33 | J11: =H11+I11 -> 93237.23 | K11: =F11-J11 -> 18596.263 | L11: =IFERROR(K11/B11,0) -> 0.050395925 | M11: =INDEX(Parametros!$C$26:$C$43,MATCH($A11,Parametros!$A$26:$A$43,0)) -> 360000 | N11: =IFERROR(B11/M11,0) -> 1.0250092 | O11: =SUMIFS(Ventas!$Y$2:$Y$1620,Ventas!$C$2:$C$1620,$A11) -> 46 | P11: =IFERROR(B11/O11,0) -> 8021.8109
A12: =Parametros!$A$33 -> 45870 | B12: =SUMIFS(Ventas!$P$2:$P$1620,Ventas!$C$2:$C$1620,$A12) -> 244108.86 | C12: =SUMIFS(Ventas!$R$2:$R$1620,Ventas!$C$2:$C$1620,$A12) -> 152511.9 | D12: =SUMIFS(Ventas!$S$2:$S$1620,Ventas!$C$2:$C$1620,$A12) -> 8246.05 | E12: =SUMIFS(Ventas!$T$2:$T$1620,Ventas!$C$2:$C$1620,$A12) -> 8207.7571 | F12: =B12-C12-D12-E12 -> 75143.155 | G12: =IFERROR(F12/B12,0) -> 0.30782642 | H12: =SUMIFS(Gastos!$D$2:$D$217,Gastos!$A$2:$A$217,$A12,Gastos!$C$2:$C$217,"Fijo") -> 66539.08 | I12: =SUMIFS(Gastos!$D$2:$D$217,Gastos!$A$2:$A$217,$A12,Gastos!$C$2:$C$217,"Variable") -> 20098.06 | J12: =H12+I12 -> 86637.14 | K12: =F12-J12 -> -11493.985 | L12: =IFERROR(K12/B12,0) -> -0.047085489 | M12: =INDEX(Parametros!$C$26:$C$43,MATCH($A12,Parametros!$A$26:$A$43,0)) -> 250000 | N12: =IFERROR(B12/M12,0) -> 0.97643543 | O12: =SUMIFS(Ventas!$Y$2:$Y$1620,Ventas!$C$2:$C$1620,$A12) -> 33 | P12: =IFERROR(B12/O12,0) -> 7397.2381
A13: =Parametros!$A$34 -> 45901 | B13: =SUMIFS(Ventas!$P$2:$P$1620,Ventas!$C$2:$C$1620,$A13) -> 333535.39 | C13: =SUMIFS(Ventas!$R$2:$R$1620,Ventas!$C$2:$C$1620,$A13) -> 209369.24 | D13: =SUMIFS(Ventas!$S$2:$S$1620,Ventas!$C$2:$C$1620,$A13) -> 12385.1 | E13: =SUMIFS(Ventas!$T$2:$T$1620,Ventas!$C$2:$C$1620,$A13) -> 11339.889 | F13: =B13-C13-D13-E13 -> 100441.16 | G13: =IFERROR(F13/B13,0) -> 0.30114093 | H13: =SUMIFS(Gastos!$D$2:$D$217,Gastos!$A$2:$A$217,$A13,Gastos!$C$2:$C$217,"Fijo") -> 67543.52 | I13: =SUMIFS(Gastos!$D$2:$D$217,Gastos!$A$2:$A$217,$A13,Gastos!$C$2:$C$217,"Variable") -> 26830.24 | J13: =H13+I13 -> 94373.76 | K13: =F13-J13 -> 6067.3969 | L13: =IFERROR(K13/B13,0) -> 0.018191164 | M13: =INDEX(Parametros!$C$26:$C$43,MATCH($A13,Parametros!$A$26:$A$43,0)) -> 340000 | N13: =IFERROR(B13/M13,0) -> 0.98098643 | O13: =SUMIFS(Ventas!$Y$2:$Y$1620,Ventas!$C$2:$C$1620,$A13) -> 47 | P13: =IFERROR(B13/O13,0) -> 7096.4976
A14: =Parametros!$A$35 -> 45931 | B14: =SUMIFS(Ventas!$P$2:$P$1620,Ventas!$C$2:$C$1620,$A14) -> 361634.8 | C14: =SUMIFS(Ventas!$R$2:$R$1620,Ventas!$C$2:$C$1620,$A14) -> 227231.6 | D14: =SUMIFS(Ventas!$S$2:$S$1620,Ventas!$C$2:$C$1620,$A14) -> 15231.6 | E14: =SUMIFS(Ventas!$T$2:$T$1620,Ventas!$C$2:$C$1620,$A14) -> 12461.574 | F14: =B14-C14-D14-E14 -> 106710.03 | G14: =IFERROR(F14/B14,0) -> 0.29507677 | H14: =SUMIFS(Gastos!$D$2:$D$217,Gastos!$A$2:$A$217,$A14,Gastos!$C$2:$C$217,"Fijo") -> 72158.79 | I14: =SUMIFS(Gastos!$D$2:$D$217,Gastos!$A$2:$A$217,$A14,Gastos!$C$2:$C$217,"Variable") -> 23387.59 | J14: =H14+I14 -> 95546.38 | K14: =F14-J14 -> 11163.648 | L14: =IFERROR(K14/B14,0) -> 0.03086995 | M14: =INDEX(Parametros!$C$26:$C$43,MATCH($A14,Parametros!$A$26:$A$43,0)) -> 370000 | N14: =IFERROR(B14/M14,0) -> 0.97739135 | O14: =SUMIFS(Ventas!$Y$2:$Y$1620,Ventas!$C$2:$C$1620,$A14) -> 54 | P14: =IFERROR(B14/O14,0) -> 6696.9408
A15: =Parametros!$A$36 -> 45962 | B15: =SUMIFS(Ventas!$P$2:$P$1620,Ventas!$C$2:$C$1620,$A15) -> 432903.56 | C15: =SUMIFS(Ventas!$R$2:$R$1620,Ventas!$C$2:$C$1620,$A15) -> 275510.87 | D15: =SUMIFS(Ventas!$S$2:$S$1620,Ventas!$C$2:$C$1620,$A15) -> 14474.8 | E15: =SUMIFS(Ventas!$T$2:$T$1620,Ventas!$C$2:$C$1620,$A15) -> 14447.654 | F15: =B15-C15-D15-E15 -> 128470.23 | G15: =IFERROR(F15/B15,0) -> 0.2967641 | H15: =SUMIFS(Gastos!$D$2:$D$217,Gastos!$A$2:$A$217,$A15,Gastos!$C$2:$C$217,"Fijo") -> 71991.07 | I15: =SUMIFS(Gastos!$D$2:$D$217,Gastos!$A$2:$A$217,$A15,Gastos!$C$2:$C$217,"Variable") -> 22332.21 | J15: =H15+I15 -> 94323.28 | K15: =F15-J15 -> 34146.955 | L15: =IFERROR(K15/B15,0) -> 0.078878895 | M15: =INDEX(Parametros!$C$26:$C$43,MATCH($A15,Parametros!$A$26:$A$43,0)) -> 390000 | N15: =IFERROR(B15/M15,0) -> 1.1100091 | O15: =SUMIFS(Ventas!$Y$2:$Y$1620,Ventas!$C$2:$C$1620,$A15) -> 49 | P15: =IFERROR(B15/O15,0) -> 8834.7666
A16: =Parametros!$A$37 -> 45992 | B16: =SUMIFS(Ventas!$P$2:$P$1620,Ventas!$C$2:$C$1620,$A16) -> 369951.02 | C16: =SUMIFS(Ventas!$R$2:$R$1620,Ventas!$C$2:$C$1620,$A16) -> 231230.09 | D16: =SUMIFS(Ventas!$S$2:$S$1620,Ventas!$C$2:$C$1620,$A16) -> 13672.35 | E16: =SUMIFS(Ventas!$T$2:$T$1620,Ventas!$C$2:$C$1620,$A16) -> 12283.856 | F16: =B16-C16-D16-E16 -> 112764.72 | G16: =IFERROR(F16/B16,0) -> 0.30480986 | H16: =SUMIFS(Gastos!$D$2:$D$217,Gastos!$A$2:$A$217,$A16,Gastos!$C$2:$C$217,"Fijo") -> 72037.61 | I16: =SUMIFS(Gastos!$D$2:$D$217,Gastos!$A$2:$A$217,$A16,Gastos!$C$2:$C$217,"Variable") -> 25395.67 | J16: =H16+I16 -> 97433.28 | K16: =F16-J16 -> 15331.438 | L16: =IFERROR(K16/B16,0) -> 0.041441806 | M16: =INDEX(Parametros!$C$26:$C$43,MATCH($A16,Parametros!$A$26:$A$43,0)) -> 360000 | N16: =IFERROR(B16/M16,0) -> 1.0276417 | O16: =SUMIFS(Ventas!$Y$2:$Y$1620,Ventas!$C$2:$C$1620,$A16) -> 43 | P16: =IFERROR(B16/O16,0) -> 8603.512
A17: =Parametros!$A$38 -> 46023 | B17: =SUMIFS(Ventas!$P$2:$P$1620,Ventas!$C$2:$C$1620,$A17) -> 337299.01 | C17: =SUMIFS(Ventas!$R$2:$R$1620,Ventas!$C$2:$C$1620,$A17) -> 213619.98 | D17: =SUMIFS(Ventas!$S$2:$S$1620,Ventas!$C$2:$C$1620,$A17) -> 9782.5 | E17: =SUMIFS(Ventas!$T$2:$T$1620,Ventas!$C$2:$C$1620,$A17) -> 11495.058 | F17: =B17-C17-D17-E17 -> 102401.48 | G17: =IFERROR(F17/B17,0) -> 0.30359258 | H17: =SUMIFS(Gastos!$D$2:$D$217,Gastos!$A$2:$A$217,$A17,Gastos!$C$2:$C$217,"Fijo") -> 67694.27 | I17: =SUMIFS(Gastos!$D$2:$D$217,Gastos!$A$2:$A$217,$A17,Gastos!$C$2:$C$217,"Variable") -> 21004.99 | J17: =H17+I17 -> 88699.26 | K17: =F17-J17 -> 13702.216 | L17: =IFERROR(K17/B17,0) -> 0.040623352 | M17: =INDEX(Parametros!$C$26:$C$43,MATCH($A17,Parametros!$A$26:$A$43,0)) -> 335000 | N17: =IFERROR(B17/M17,0) -> 1.0068627 | O17: =SUMIFS(Ventas!$Y$2:$Y$1620,Ventas!$C$2:$C$1620,$A17) -> 42 | P17: =IFERROR(B17/O17,0) -> 8030.9288
A18: =Parametros!$A$39 -> 46054 | B18: =SUMIFS(Ventas!$P$2:$P$1620,Ventas!$C$2:$C$1620,$A18) -> 352386.62 | C18: =SUMIFS(Ventas!$R$2:$R$1620,Ventas!$C$2:$C$1620,$A18) -> 221696.29 | D18: =SUMIFS(Ventas!$S$2:$S$1620,Ventas!$C$2:$C$1620,$A18) -> 10500.1 | E18: =SUMIFS(Ventas!$T$2:$T$1620,Ventas!$C$2:$C$1620,$A18) -> 12375.227 | F18: =B18-C18-D18-E18 -> 107815.01 | G18: =IFERROR(F18/B18,0) -> 0.30595659 | H18: =SUMIFS(Gastos!$D$2:$D$217,Gastos!$A$2:$A$217,$A18,Gastos!$C$2:$C$217,"Fijo") -> 70239.53 | I18: =SUMIFS(Gastos!$D$2:$D$217,Gastos!$A$2:$A$217,$A18,Gastos!$C$2:$C$217,"Variable") -> 26090.1 | J18: =H18+I18 -> 96329.63 | K18: =F18-J18 -> 11485.381 | L18: =IFERROR(K18/B18,0) -> 0.032593124 | M18: =INDEX(Parametros!$C$26:$C$43,MATCH($A18,Parametros!$A$26:$A$43,0)) -> 355000 | N18: =IFERROR(B18/M18,0) -> 0.99263838 | O18: =SUMIFS(Ventas!$Y$2:$Y$1620,Ventas!$C$2:$C$1620,$A18) -> 48 | P18: =IFERROR(B18/O18,0) -> 7341.388
A19: =Parametros!$A$40 -> 46082 | B19: =SUMIFS(Ventas!$P$2:$P$1620,Ventas!$C$2:$C$1620,$A19) -> 398590.96 | C19: =SUMIFS(Ventas!$R$2:$R$1620,Ventas!$C$2:$C$1620,$A19) -> 246099.68 | D19: =SUMIFS(Ventas!$S$2:$S$1620,Ventas!$C$2:$C$1620,$A19) -> 12413.1 | E19: =SUMIFS(Ventas!$T$2:$T$1620,Ventas!$C$2:$C$1620,$A19) -> 14138.794 | F19: =B19-C19-D19-E19 -> 125939.39 | G19: =IFERROR(F19/B19,0) -> 0.31596148 | H19: =SUMIFS(Gastos!$D$2:$D$217,Gastos!$A$2:$A$217,$A19,Gastos!$C$2:$C$217,"Fijo") -> 70765.18 | I19: =SUMIFS(Gastos!$D$2:$D$217,Gastos!$A$2:$A$217,$A19,Gastos!$C$2:$C$217,"Variable") -> 20986.23 | J19: =H19+I19 -> 91751.41 | K19: =F19-J19 -> 34187.979 | L19: =IFERROR(K19/B19,0) -> 0.085772088 | M19: =INDEX(Parametros!$C$26:$C$43,MATCH($A19,Parametros!$A$26:$A$43,0)) -> 400000 | N19: =IFERROR(B19/M19,0) -> 0.9964774 | O19: =SUMIFS(Ventas!$Y$2:$Y$1620,Ventas!$C$2:$C$1620,$A19) -> 52 | P19: =IFERROR(B19/O19,0) -> 7665.2108
A20: =Parametros!$A$41 -> 46113 | B20: =SUMIFS(Ventas!$P$2:$P$1620,Ventas!$C$2:$C$1620,$A20) -> 393675.57 | C20: =SUMIFS(Ventas!$R$2:$R$1620,Ventas!$C$2:$C$1620,$A20) -> 238161.45 | D20: =SUMIFS(Ventas!$S$2:$S$1620,Ventas!$C$2:$C$1620,$A20) -> 11844.5 | E20: =SUMIFS(Ventas!$T$2:$T$1620,Ventas!$C$2:$C$1620,$A20) -> 13851.472 | F20: =B20-C20-D20-E20 -> 129818.15 | G20: =IFERROR(F20/B20,0) -> 0.32975922 | H20: =SUMIFS(Gastos!$D$2:$D$217,Gastos!$A$2:$A$217,$A20,Gastos!$C$2:$C$217,"Fijo") -> 69103.85 | I20: =SUMIFS(Gastos!$D$2:$D$217,Gastos!$A$2:$A$217,$A20,Gastos!$C$2:$C$217,"Variable") -> 19895.85 | J20: =H20+I20 -> 88999.7 | K20: =F20-J20 -> 40818.447 | L20: =IFERROR(K20/B20,0) -> 0.1036855 | M20: =INDEX(Parametros!$C$26:$C$43,MATCH($A20,Parametros!$A$26:$A$43,0)) -> 400000 | N20: =IFERROR(B20/M20,0) -> 0.98418891 | O20: =SUMIFS(Ventas!$Y$2:$Y$1620,Ventas!$C$2:$C$1620,$A20) -> 57 | P20: =IFERROR(B20/O20,0) -> 6906.5889
A21: =Parametros!$A$42 -> 46143 | B21: =SUMIFS(Ventas!$P$2:$P$1620,Ventas!$C$2:$C$1620,$A21) -> 398935.23 | C21: =SUMIFS(Ventas!$R$2:$R$1620,Ventas!$C$2:$C$1620,$A21) -> 241362.38 | D21: =SUMIFS(Ventas!$S$2:$S$1620,Ventas!$C$2:$C$1620,$A21) -> 12824.75 | E21: =SUMIFS(Ventas!$T$2:$T$1620,Ventas!$C$2:$C$1620,$A21) -> 13830.895 | F21: =B21-C21-D21-E21 -> 130917.21 | G21: =IFERROR(F21/B21,0) -> 0.32816656 | H21: =SUMIFS(Gastos!$D$2:$D$217,Gastos!$A$2:$A$217,$A21,Gastos!$C$2:$C$217,"Fijo") -> 70575.85 | I21: =SUMIFS(Gastos!$D$2:$D$217,Gastos!$A$2:$A$217,$A21,Gastos!$C$2:$C$217,"Variable") -> 24047.56 | J21: =H21+I21 -> 94623.41 | K21: =F21-J21 -> 36293.795 | L21: =IFERROR(K21/B21,0) -> 0.09097666 | M21: =INDEX(Parametros!$C$26:$C$43,MATCH($A21,Parametros!$A$26:$A$43,0)) -> 400000 | N21: =IFERROR(B21/M21,0) -> 0.99733808 | O21: =SUMIFS(Ventas!$Y$2:$Y$1620,Ventas!$C$2:$C$1620,$A21) -> 56 | P21: =IFERROR(B21/O21,0) -> 7123.8435
A22: =Parametros!$A$43 -> 46174 | B22: =SUMIFS(Ventas!$P$2:$P$1620,Ventas!$C$2:$C$1620,$A22) -> 349173.98 | C22: =SUMIFS(Ventas!$R$2:$R$1620,Ventas!$C$2:$C$1620,$A22) -> 215075.15 | D22: =SUMIFS(Ventas!$S$2:$S$1620,Ventas!$C$2:$C$1620,$A22) -> 12450.8 | E22: =SUMIFS(Ventas!$T$2:$T$1620,Ventas!$C$2:$C$1620,$A22) -> 11830.216 | F22: =B22-C22-D22-E22 -> 109817.82 | G22: =IFERROR(F22/B22,0) -> 0.31450746 | H22: =SUMIFS(Gastos!$D$2:$D$217,Gastos!$A$2:$A$217,$A22,Gastos!$C$2:$C$217,"Fijo") -> 71990.58 | I22: =SUMIFS(Gastos!$D$2:$D$217,Gastos!$A$2:$A$217,$A22,Gastos!$C$2:$C$217,"Variable") -> 22011.78 | J22: =H22+I22 -> 94002.36 | K22: =F22-J22 -> 15815.463 | L22: =IFERROR(K22/B22,0) -> 0.045293933 | M22: =INDEX(Parametros!$C$26:$C$43,MATCH($A22,Parametros!$A$26:$A$43,0)) -> 370000 | N22: =IFERROR(B22/M22,0) -> 0.94371347 | O22: =SUMIFS(Ventas!$Y$2:$Y$1620,Ventas!$C$2:$C$1620,$A22) -> 50 | P22: =IFERROR(B22/O22,0) -> 6983.4797
A23: TOTAL 18 meses | B23: =SUM(B5:B22) -> 6469595.4 | C23: =SUM(C5:C22) -> 4042477.8 | D23: =SUM(D5:D22) -> 211413.05 | E23: =SUM(E5:E22) -> 220979.79 | F23: =SUM(F5:F22) -> 1994724.8 | G23: =IFERROR(F23/B23,0) -> 0.30832296 | H23: =SUM(H5:H22) -> 1250656.4 | I23: =SUM(I5:I22) -> 410156.24 | J23: =SUM(J5:J22) -> 1660812.6 | K23: =SUM(K5:K22) -> 333912.2 | L23: =IFERROR(K23/B23,0) -> 0.051612532 | M23: =SUM(M5:M22) -> 6490000 | N23: =IFERROR(B23/M23,0) -> 0.996856 | O23: =SUM(O5:O22) -> 868 | P23: =IFERROR(B23/O23,0) -> 7453.4509
A25: Resumen por ejercicio
A26: Ejercicio | B26: Ingresos netos | C26: Margen bruto | D26: Margen % | E26: Gastos | F26: EBITDA | G26: EBITDA %
A27: 2025 (12 meses) | B27: =SUM(B5:B16) -> 4239534 | C27: =SUM(F5:F16) -> 1288015.8 | D27: =IFERROR(C27/B27,0) -> 0.30381069 | E27: =SUM(J5:J16) -> 1106406.8 | F27: =SUM(K5:K16) -> 181608.92 | G27: =IFERROR(F27/B27,0) -> 0.042837
A28: 2026 (6 meses) | B28: =SUM(B17:B22) -> 2230061.4 | C28: =SUM(F17:F22) -> 706709.05 | D28: =IFERROR(C28/B28,0) -> 0.31690117 | E28: =SUM(J17:J22) -> 554405.77 | F28: =SUM(K17:K22) -> 152303.28 | G28: =IFERROR(F28/B28,0) -> 0.068295556

Sheet KPIs
A1: CUADRO DE MANDO — acumulado ene-2025 / jun-2026
A2: Todos los bloques leen la hoja Ventas con SUMIFS. Cambia un supuesto en Parametros y este cuadro se actualiza.
A4: VENTAS POR PAÍS
A5: País | B5: Ingresos netos | C5: Margen bruto € | D5: Margen % | E5: Nº pedidos | F5: % s/ ventas
A6: España | B6: =SUMIFS(Ventas!$P$2:$P$1620,Ventas!$E$2:$E$1620,$A6) -> 3440618 | C6: =SUMIFS(Ventas!$U$2:$U$1620,Ventas!$E$2:$E$1620,$A6) -> 1110498.4 | D6: =IFERROR(C6/B6,0) -> 0.32276132 | E6: =SUMIFS(Ventas!$Y$2:$Y$1620,Ventas!$E$2:$E$1620,$A6) -> 479 | F6: =IFERROR(B6/$B$9,0) -> 0.53181347
A7: Alemania | B7: =SUMIFS(Ventas!$P$2:$P$1620,Ventas!$E$2:$E$1620,$A7) -> 1760409.4 | C7: =SUMIFS(Ventas!$U$2:$U$1620,Ventas!$E$2:$E$1620,$A7) -> 501447.09 | D7: =IFERROR(C7/B7,0) -> 0.28484686 | E7: =SUMIFS(Ventas!$Y$2:$Y$1620,Ventas!$E$2:$E$1620,$A7) -> 211 | F7: =IFERROR(B7/$B$9,0) -> 0.27210502
A8: Francia | B8: =SUMIFS(Ventas!$P$2:$P$1620,Ventas!$E$2:$E$1620,$A8) -> 1268568 | C8: =SUMIFS(Ventas!$U$2:$U$1620,Ventas!$E$2:$E$1620,$A8) -> 382779.33 | D8: =IFERROR(C8/B8,0) -> 0.30174127 | E8: =SUMIFS(Ventas!$Y$2:$Y$1620,Ventas!$E$2:$E$1620,$A8) -> 178 | F8: =IFERROR(B8/$B$9,0) -> 0.19608151
A9: TOTAL | B9: =SUM(B6:B8) -> 6469595.4 | C9: =SUM(C6:C8) -> 1994724.8 | D9: =IFERROR(C9/B9,0) -> 0.30832296 | E9: =SUM(E6:E8) -> 868 | F9: =IFERROR(B9/B9,0) -> 1
A11: VENTAS POR FAMILIA DE PRODUCTO
A12: Familia | B12: Ingresos netos | C12: Margen bruto € | D12: Margen % | E12: Nº pedidos | F12: % s/ ventas
A13: Autotaladrante | B13: =SUMIFS(Ventas!$P$2:$P$1620,Ventas!$J$2:$J$1620,$A13) -> 689498.52 | C13: =SUMIFS(Ventas!$U$2:$U$1620,Ventas!$J$2:$J$1620,$A13) -> 208206.16 | D13: =IFERROR(C13/B13,0) -> 0.30196753 | E13: =SUMIFS(Ventas!$Y$2:$Y$1620,Ventas!$J$2:$J$1620,$A13) -> 136 | F13: =IFERROR(B13/$B$18,0) -> 0.10657521
A14: Especial | B14: =SUMIFS(Ventas!$P$2:$P$1620,Ventas!$J$2:$J$1620,$A14) -> 1738284.3 | C14: =SUMIFS(Ventas!$U$2:$U$1620,Ventas!$J$2:$J$1620,$A14) -> 544611.04 | D14: =IFERROR(C14/B14,0) -> 0.31330379 | E14: =SUMIFS(Ventas!$Y$2:$Y$1620,Ventas!$J$2:$J$1620,$A14) -> 142 | F14: =IFERROR(B14/$B$18,0) -> 0.26868516
A15: Inoxidable | B15: =SUMIFS(Ventas!$P$2:$P$1620,Ventas!$J$2:$J$1620,$A15) -> 1557648.5 | C15: =SUMIFS(Ventas!$U$2:$U$1620,Ventas!$J$2:$J$1620,$A15) -> 494551.34 | D15: =IFERROR(C15/B15,0) -> 0.31749867 | E15: =SUMIFS(Ventas!$Y$2:$Y$1620,Ventas!$J$2:$J$1620,$A15) -> 136 | F15: =IFERROR(B15/$B$18,0) -> 0.24076444
A16: Madera | B16: =SUMIFS(Ventas!$P$2:$P$1620,Ventas!$J$2:$J$1620,$A16) -> 599495.6 | C16: =SUMIFS(Ventas!$U$2:$U$1620,Ventas!$J$2:$J$1620,$A16) -> 169585.56 | D16: =IFERROR(C16/B16,0) -> 0.28288041 | E16: =SUMIFS(Ventas!$Y$2:$Y$1620,Ventas!$J$2:$J$1620,$A16) -> 137 | F16: =IFERROR(B16/$B$18,0) -> 0.092663537
A17: Métrica | B17: =SUMIFS(Ventas!$P$2:$P$1620,Ventas!$J$2:$J$1620,$A17) -> 1884668.5 | C17: =SUMIFS(Ventas!$U$2:$U$1620,Ventas!$J$2:$J$1620,$A17) -> 577770.71 | D17: =IFERROR(C17/B17,0) -> 0.30656358 | E17: =SUMIFS(Ventas!$Y$2:$Y$1620,Ventas!$J$2:$J$1620,$A17) -> 317 | F17: =IFERROR(B17/$B$18,0) -> 0.29131165
A18: TOTAL | B18: =SUM(B13:B17) -> 6469595.4 | C18: =SUM(C13:C17) -> 1994724.8 | D18: =IFERROR(C18/B18,0) -> 0.30832296 | E18: =SUM(E13:E17) -> 868 | F18: =IFERROR(B18/B18,0) -> 1
A20: VENTAS POR CANAL
A21: Canal | B21: Ingresos netos | C21: Margen bruto € | D21: Margen % | E21: Nº pedidos | F21: % s/ ventas
A22: Distribuidor | B22: =SUMIFS(Ventas!$P$2:$P$1620,Ventas!$F$2:$F$1620,$A22) -> 3245561.4 | C22: =SUMIFS(Ventas!$U$2:$U$1620,Ventas!$F$2:$F$1620,$A22) -> 940030.93 | D22: =IFERROR(C22/B22,0) -> 0.28963585 | E22: =SUMIFS(Ventas!$Y$2:$Y$1620,Ventas!$F$2:$F$1620,$A22) -> 405 | F22: =IFERROR(B22/$B$26,0) -> 0.50166373
A23: OEM / Industria | B23: =SUMIFS(Ventas!$P$2:$P$1620,Ventas!$F$2:$F$1620,$A23) -> 2377293.7 | C23: =SUMIFS(Ventas!$U$2:$U$1620,Ventas!$F$2:$F$1620,$A23) -> 745642.26 | D23: =IFERROR(C23/B23,0) -> 0.31365172 | E23: =SUMIFS(Ventas!$Y$2:$Y$1620,Ventas!$F$2:$F$1620,$A23) -> 286 | F23: =IFERROR(B23/$B$26,0) -> 0.36745631
A24: Ferretería | B24: =SUMIFS(Ventas!$P$2:$P$1620,Ventas!$F$2:$F$1620,$A24) -> 802151.76 | C24: =SUMIFS(Ventas!$U$2:$U$1620,Ventas!$F$2:$F$1620,$A24) -> 290078.2 | D24: =IFERROR(C24/B24,0) -> 0.36162509 | E24: =SUMIFS(Ventas!$Y$2:$Y$1620,Ventas!$F$2:$F$1620,$A24) -> 150 | F24: =IFERROR(B24/$B$26,0) -> 0.12398793
A25: Ecommerce | B25: =SUMIFS(Ventas!$P$2:$P$1620,Ventas!$F$2:$F$1620,$A25) -> 44588.633 | C25: =SUMIFS(Ventas!$U$2:$U$1620,Ventas!$F$2:$F$1620,$A25) -> 18973.418 | D25: =IFERROR(C25/B25,0) -> 0.42552142 | E25: =SUMIFS(Ventas!$Y$2:$Y$1620,Ventas!$F$2:$F$1620,$A25) -> 27 | F25: =IFERROR(B25/$B$26,0) -> 0.006892028
A26: TOTAL | B26: =SUM(B22:B25) -> 6469595.4 | C26: =SUM(C22:C25) -> 1994724.8 | D26: =IFERROR(C26/B26,0) -> 0.30832296 | E26: =SUM(E22:E25) -> 868 | F26: =IFERROR(B26/B26,0) -> 1
A28: VENTAS POR COMERCIAL
A29: Comercial | B29: Ingresos netos | C29: Margen bruto € | D29: Margen % | E29: Nº pedidos | F29: % s/ ventas
A30: Alberto Ruiz | B30: =SUMIFS(Ventas!$P$2:$P$1620,Ventas!$G$2:$G$1620,$A30) -> 2044959.5 | C30: =SUMIFS(Ventas!$U$2:$U$1620,Ventas!$G$2:$G$1620,$A30) -> 660233.7 | D30: =IFERROR(C30/B30,0) -> 0.32285906 | E30: =SUMIFS(Ventas!$Y$2:$Y$1620,Ventas!$G$2:$G$1620,$A30) -> 252 | F30: =IFERROR(B30/$B$35,0) -> 0.31608769
A31: Camille Girard | B31: =SUMIFS(Ventas!$P$2:$P$1620,Ventas!$G$2:$G$1620,$A31) -> 1268568 | C31: =SUMIFS(Ventas!$U$2:$U$1620,Ventas!$G$2:$G$1620,$A31) -> 382779.33 | D31: =IFERROR(C31/B31,0) -> 0.30174127 | E31: =SUMIFS(Ventas!$Y$2:$Y$1620,Ventas!$G$2:$G$1620,$A31) -> 178 | F31: =IFERROR(B31/$B$35,0) -> 0.19608151
A32: Canal online | B32: =SUMIFS(Ventas!$P$2:$P$1620,Ventas!$G$2:$G$1620,$A32) -> 44588.633 | C32: =SUMIFS(Ventas!$U$2:$U$1620,Ventas!$G$2:$G$1620,$A32) -> 18973.418 | D32: =IFERROR(C32/B32,0) -> 0.42552142 | E32: =SUMIFS(Ventas!$Y$2:$Y$1620,Ventas!$G$2:$G$1620,$A32) -> 27 | F32: =IFERROR(B32/$B$35,0) -> 0.006892028
A33: Klaus Berger | B33: =SUMIFS(Ventas!$P$2:$P$1620,Ventas!$G$2:$G$1620,$A33) -> 1760409.4 | C33: =SUMIFS(Ventas!$U$2:$U$1620,Ventas!$G$2:$G$1620,$A33) -> 501447.09 | D33: =IFERROR(C33/B33,0) -> 0.28484686 | E33: =SUMIFS(Ventas!$Y$2:$Y$1620,Ventas!$G$2:$G$1620,$A33) -> 211 | F33: =IFERROR(B33/$B$35,0) -> 0.27210502
A34: Nuria Salas | B34: =SUMIFS(Ventas!$P$2:$P$1620,Ventas!$G$2:$G$1620,$A34) -> 1351069.9 | C34: =SUMIFS(Ventas!$U$2:$U$1620,Ventas!$G$2:$G$1620,$A34) -> 431291.28 | D34: =IFERROR(C34/B34,0) -> 0.31922203 | E34: =SUMIFS(Ventas!$Y$2:$Y$1620,Ventas!$G$2:$G$1620,$A34) -> 200 | F34: =IFERROR(B34/$B$35,0) -> 0.20883375
A35: TOTAL | B35: =SUM(B30:B34) -> 6469595.4 | C35: =SUM(C30:C34) -> 1994724.8 | D35: =IFERROR(C35/B35,0) -> 0.30832296 | E35: =SUM(E30:E34) -> 868 | F35: =IFERROR(B35/B35,0) -> 1
A37: TOP 10 CLIENTES POR FACTURACIÓN
A38: Cliente | B38: País | C38: Ingresos netos | D38: Margen bruto € | E38: Margen % | F38: Pendiente cobro
A39: Hanseatic Fasteners GmbH | B39: =INDEX(Clientes!$B$2:$B$39,MATCH($A39,Clientes!$A$2:$A$39,0)) -> Alemania | C39: =SUMIFS(Ventas!$P$2:$P$1620,Ventas!$D$2:$D$1620,$A39) -> 313935.47 | D39: =SUMIFS(Ventas!$U$2:$U$1620,Ventas!$D$2:$D$1620,$A39) -> 86703.112 | E39: =IFERROR(D39/C39,0) -> 0.27618132 | F39: =INDEX(Clientes!$L$2:$L$39,MATCH($A39,Clientes!$A$2:$A$39,0)) -> 55466.569
A40: Montajes Industriales Vigo SL | B40: =INDEX(Clientes!$B$2:$B$39,MATCH($A40,Clientes!$A$2:$A$39,0)) -> España | C40: =SUMIFS(Ventas!$P$2:$P$1620,Ventas!$D$2:$D$1620,$A40) -> 290874.72 | D40: =SUMIFS(Ventas!$U$2:$U$1620,Ventas!$D$2:$D$1620,$A40) -> 94487.013 | E40: =IFERROR(D40/C40,0) -> 0.32483748 | F40: =INDEX(Clientes!$L$2:$L$39,MATCH($A40,Clientes!$A$2:$A$39,0)) -> 30110.51
A41: Bayern Befestigung GmbH | B41: =INDEX(Clientes!$B$2:$B$39,MATCH($A41,Clientes!$A$2:$A$39,0)) -> Alemania | C41: =SUMIFS(Ventas!$P$2:$P$1620,Ventas!$D$2:$D$1620,$A41) -> 279795.15 | D41: =SUMIFS(Ventas!$U$2:$U$1620,Ventas!$D$2:$D$1620,$A41) -> 76639.395 | E41: =IFERROR(D41/C41,0) -> 0.27391252 | F41: =INDEX(Clientes!$L$2:$L$39,MATCH($A41,Clientes!$A$2:$A$39,0)) -> 10401.048
A42: Schrauben Nord GmbH | B42: =INDEX(Clientes!$B$2:$B$39,MATCH($A42,Clientes!$A$2:$A$39,0)) -> Alemania | C42: =SUMIFS(Ventas!$P$2:$P$1620,Ventas!$D$2:$D$1620,$A42) -> 279560.77 | D42: =SUMIFS(Ventas!$U$2:$U$1620,Ventas!$D$2:$D$1620,$A42) -> 77428.641 | E42: =IFERROR(D42/C42,0) -> 0.27696533 | F42: =INDEX(Clientes!$L$2:$L$39,MATCH($A42,Clientes!$A$2:$A$39,0)) -> 39936.644
A43: Aceros del Norte SA | B43: =INDEX(Clientes!$B$2:$B$39,MATCH($A43,Clientes!$A$2:$A$39,0)) -> España | C43: =SUMIFS(Ventas!$P$2:$P$1620,Ventas!$D$2:$D$1620,$A43) -> 268007.9 | D43: =SUMIFS(Ventas!$U$2:$U$1620,Ventas!$D$2:$D$1620,$A43) -> 80096.429 | E43: =IFERROR(D43/C43,0) -> 0.29885846 | F43: =INDEX(Clientes!$L$2:$L$39,MATCH($A43,Clientes!$A$2:$A$39,0)) -> 21557.422
A44: Suministros Torres SA | B44: =INDEX(Clientes!$B$2:$B$39,MATCH($A44,Clientes!$A$2:$A$39,0)) -> España | C44: =SUMIFS(Ventas!$P$2:$P$1620,Ventas!$D$2:$D$1620,$A44) -> 265223.27 | D44: =SUMIFS(Ventas!$U$2:$U$1620,Ventas!$D$2:$D$1620,$A44) -> 80529.702 | E44: =IFERROR(D44/C44,0) -> 0.30362986 | F44: =INDEX(Clientes!$L$2:$L$39,MATCH($A44,Clientes!$A$2:$A$39,0)) -> 39261.903
A45: Grupo Ferretero Andalucía SA | B45: =INDEX(Clientes!$B$2:$B$39,MATCH($A45,Clientes!$A$2:$A$39,0)) -> España | C45: =SUMIFS(Ventas!$P$2:$P$1620,Ventas!$D$2:$D$1620,$A45) -> 263571.55 | D45: =SUMIFS(Ventas!$U$2:$U$1620,Ventas!$D$2:$D$1620,$A45) -> 79923.799 | E45: =IFERROR(D45/C45,0) -> 0.30323379 | F45: =INDEX(Clientes!$L$2:$L$39,MATCH($A45,Clientes!$A$2:$A$39,0)) -> 34681.476
A46: Distribuciones Metálicas Levante SL | B46: =INDEX(Clientes!$B$2:$B$39,MATCH($A46,Clientes!$A$2:$A$39,0)) -> España | C46: =SUMIFS(Ventas!$P$2:$P$1620,Ventas!$D$2:$D$1620,$A46) -> 249578.96 | D46: =SUMIFS(Ventas!$U$2:$U$1620,Ventas!$D$2:$D$1620,$A46) -> 76627.565 | E46: =IFERROR(D46/C46,0) -> 0.30702734 | F46: =INDEX(Clientes!$L$2:$L$39,MATCH($A46,Clientes!$A$2:$A$39,0)) -> 24377.751
A47: Stahlhandel Ruhr GmbH | B47: =INDEX(Clientes!$B$2:$B$39,MATCH($A47,Clientes!$A$2:$A$39,0)) -> Alemania | C47: =SUMIFS(Ventas!$P$2:$P$1620,Ventas!$D$2:$D$1620,$A47) -> 236461.49 | D47: =SUMIFS(Ventas!$U$2:$U$1620,Ventas!$D$2:$D$1620,$A47) -> 64314.104 | E47: =IFERROR(D47/C47,0) -> 0.27198553 | F47: =INDEX(Clientes!$L$2:$L$39,MATCH($A47,Clientes!$A$2:$A$39,0)) -> 14156.192
A48: Groupe Boulonnerie Paris SAS | B48: =INDEX(Clientes!$B$2:$B$39,MATCH($A48,Clientes!$A$2:$A$39,0)) -> Francia | C48: =SUMIFS(Ventas!$P$2:$P$1620,Ventas!$D$2:$D$1620,$A48) -> 215208.77 | D48: =SUMIFS(Ventas!$U$2:$U$1620,Ventas!$D$2:$D$1620,$A48) -> 60258.155 | E48: =IFERROR(D48/C48,0) -> 0.2799986 | F48: =INDEX(Clientes!$L$2:$L$39,MATCH($A48,Clientes!$A$2:$A$39,0)) -> 19608.158
A50: SITUACIÓN DE COBRO
A51: Estado | B51: Importe | C51: Nº líneas | D51: % s/ total
A52: Cobrado | B52: =SUMIFS(Ventas!$P$2:$P$1620,Ventas!$X$2:$X$1620,$A52) -> 5702077.5 | C52: =COUNTIFS(Ventas!$X$2:$X$1620,$A52) -> 1432 | D52: =IFERROR(B52/$B$55,0) -> 0.88136539
A53: Pendiente | B53: =SUMIFS(Ventas!$P$2:$P$1620,Ventas!$X$2:$X$1620,$A53) -> 366504.4 | C53: =COUNTIFS(Ventas!$X$2:$X$1620,$A53) -> 89 | D53: =IFERROR(B53/$B$55,0) -> 0.056650282
A54: Vencido | B54: =SUMIFS(Ventas!$P$2:$P$1620,Ventas!$X$2:$X$1620,$A54) -> 401013.54 | C54: =COUNTIFS(Ventas!$X$2:$X$1620,$A54) -> 98 | D54: =IFERROR(B54/$B$55,0) -> 0.06198433
A55: TOTAL | B55: =SUM(B52:B54) -> 6469595.4 | C55: =SUM(C52:C54) -> 1619 | D55: =IFERROR(B55/B55,0) -> 1
A57: INDICADORES GLOBALES
A58: Ingresos netos acumulados | B58: =PL_Mensual!$B$23 -> 6469595.4
A59: Margen bruto acumulado | B59: =PL_Mensual!$F$23 -> 1994724.8
A60: Margen bruto % | B60: =PL_Mensual!$G$23 -> 0.30832296
A61: Gastos de explotación acumulados | B61: =PL_Mensual!$J$23 -> 1660812.6
A62: EBITDA acumulado | B62: =PL_Mensual!$K$23 -> 333912.2
A63: EBITDA % | B63: =PL_Mensual!$L$23 -> 0.051612532
A64: Nº de pedidos | B64: =PL_Mensual!$O$23 -> 868
A65: Ticket medio por pedido | B65: =PL_Mensual!$P$23 -> 7453.4509
A66: Nº de líneas de venta | B66: =COUNTA(Ventas!$A$2:$A$1620) -> 1619
A67: Nº de clientes activos | B67: =COUNTIF(Clientes!$F$2:$F$39,">0") -> 38
A68: Cumplimiento del objetivo | B68: =PL_Mensual!$N$23 -> 0.996856
A69: Descuento medio ponderado | B69: =IFERROR(1-SUM(Ventas!$P$2:$P$1620)/SUMPRODUCT(Ventas!$L$2:$L$1620,Ventas!$M$2:$M$1620),0) -> 0.14217469
